Workbook
Name CIQWBGuid: "2cd8126d-26c3-430c-b7fa-a069e3a1fc62"
Name IQ_CH: 110000
Name IQ_CQ: 5000
Name IQ_CY: 10000
Name IQ_DAILY: 500000
Name IQ_DNTM: 700000
Name IQ_FH: 100000
Name IQ_FQ: 500
Name IQ_FWD_CY: 10001
Name IQ_FWD_CY1: 10002
Name IQ_FWD_CY2: 10003
Name IQ_FWD_FY: 1001
Name IQ_FWD_FY1: 1002
Name IQ_FWD_FY2: 1003
Name IQ_FWD_Q: 501
Name IQ_FWD_Q1: 502
Name IQ_FWD_Q2: 503
Name IQ_FY: 1000
Name IQ_LATESTK: 1000
Name IQ_LATESTQ: 500
Name IQ_LTM: 2000
Name IQ_LTMMONTH: 120000
Name IQ_MONTH: 15000
Name IQ_MTD: 800000
Name IQ_NAMES_REVISION_DATE_: 43412.7003240741
Name IQ_NTM: 6000
Name IQ_QTD: 750000
Name IQ_TODAY: 0
Name IQ_WEEK: 50000
Name IQ_YTD: 3000
Name IQ_YTDMONTH: 130000

Sheet M&A Assumptions & Analysis
A1: ="Merger Assumptions for "&D6&" & "&D7 -> Merger Assumptions for Online Company Inc & Brick 'n' Mortar Co
A3: Assumptions
A5: Transaction Inputs | F5: Scenarios
A6: Acquirer Name | D6: Online Company Inc | F6: Scenario # | G6: LIVE --> | H6: 1 | I6: 1 | J6: =+I6+1 -> 2 | K6: =+J6+1 -> 3 | L6: =+K6+1 -> 4 | M6: =+L6+1 -> 5
A7: Target Name | D7: Brick 'n' Mortar Co
A8: Acquirer Share Price | D8: ='[1]M&A Assumptions'!$C$5 -> 11.75 | F8: Synergies
A9: Target Share Price | D9: ='Target Model'!C159 -> 17.3 | F9: Revenue enhancement | H9: =+OFFSET(I9,0,$H$6-1) -> 5500 | I9: ='[2]M&A Assumptions'!$C$22 -> 5500 | J9: ='[2]M&A Assumptions'!$D$22 -> 6000 | K9: ='[2]M&A Assumptions'!$E$22 -> 6000 | L9: ='[2]M&A Assumptions'!$F$22 -> 6500 | M9: ='[2]M&A Assumptions'!$G$22 -> 6500
A10: Transaction Close Date | D10: 45838 | F10: COGS savings | H10: =+OFFSET(I10,0,$H$6-1) -> 875 | I10: ='[2]M&A Assumptions'!$C$23 -> 875 | J10: ='[2]M&A Assumptions'!$D$23 -> 875 | K10: ='[2]M&A Assumptions'!$E$23 -> 875 | L10: ='[2]M&A Assumptions'!$F$23 -> 875 | M10: ='[2]M&A Assumptions'!$G$23 -> 875
A11: Financial Reporting Units | D11: $'000s | F11: Marketing savings | H11: =+OFFSET(I11,0,$H$6-1) -> 1250 | I11: ='[2]M&A Assumptions'!$C$24 -> 1250 | J11: ='[2]M&A Assumptions'!$C$24 -> 1250 | K11: ='[2]M&A Assumptions'!$C$24 -> 1250 | L11: ='[2]M&A Assumptions'!$C$24 -> 1250 | M11: ='[2]M&A Assumptions'!$C$24 -> 1250
A12: Currency | D12: USD | F12: General & Admin savings | H12: =+OFFSET(I12,0,$H$6-1) -> 1000 | I12: ='[2]M&A Assumptions'!$C$25 -> 1000 | J12: ='[2]M&A Assumptions'!$C$25 -> 1000 | K12: ='[2]M&A Assumptions'!$C$25 -> 1000 | L12: ='[2]M&A Assumptions'!$C$25 -> 1000 | M12: ='[2]M&A Assumptions'!$C$25 -> 1000
A14: Restructuring Charges | D14: ='[2]M&A Assumptions'!$C$11 -> 2000 | F14: Synergies in Year 1 (full yr.) | H14: =+OFFSET(I14,0,$H$6-1) -> 0.3 | I14: ='[2]M&A Assumptions'!$C$27 -> 0.3 | J14: ='[2]M&A Assumptions'!$C$27 -> 0.3 | K14: ='[2]M&A Assumptions'!$C$27 -> 0.3 | L14: ='[2]M&A Assumptions'!$C$27 -> 0.3 | M14: ='[2]M&A Assumptions'!$C$27 -> 0.3
A15: Equity Issuance Fees | D15: ='[2]M&A Assumptions'!$C$12 -> 0.03 | F15: Synergies in Year 2 | H15: =+OFFSET(I15,0,$H$6-1) -> 0.65 | I15: ='[2]M&A Assumptions'!$C$28 -> 0.65 | J15: ='[2]M&A Assumptions'!$C$28 -> 0.65 | K15: ='[2]M&A Assumptions'!$C$28 -> 0.65 | L15: ='[2]M&A Assumptions'!$C$28 -> 0.65 | M15: ='[2]M&A Assumptions'!$C$28 -> 0.65
A16: Debt Issuance Fees | D16: ='[2]M&A Assumptions'!$C$13 -> 0.03 | F16: Synergies in Years 3+ | H16: =+OFFSET(I16,0,$H$6-1) -> 1 | I16: ='[2]M&A Assumptions'!$C$29 -> 1 | J16: ='[2]M&A Assumptions'!$C$29 -> 1 | K16: ='[2]M&A Assumptions'!$C$29 -> 1 | L16: ='[2]M&A Assumptions'!$C$29 -> 1 | M16: ='[2]M&A Assumptions'!$C$29 -> 1
A17: Other Closing Costs | D17: ='[2]M&A Assumptions'!$C$14 -> 2000
F18: Financing
A19: Replace Target Debt | D19: No | F19: Debt Tranche
A20: Replace Acquirer Debt | D20: Yes | F20: Senior Debt A | H20: =+OFFSET(I20,0,$H$6-1) -> 0 | I20: 0 | J20: ='[2]M&A Assumptions'!$D$33 -> 100000 | K20: ='[2]M&A Assumptions'!$E$33 -> 100000 | L20: ='[2]M&A Assumptions'!$F$33 -> 100000 | M20: ='[2]M&A Assumptions'!$G$33 -> 100000
F21: Senior Debt B | H21: =+OFFSET(I21,0,$H$6-1) -> 0 | I21: ='[2]M&A Assumptions'!$C$34 -> 0 | J21: ='[2]M&A Assumptions'!$D$34 -> 0 | K21: ='[2]M&A Assumptions'!$E$34 -> 50000 | L21: ='[2]M&A Assumptions'!$F$34 -> 50000 | M21: ='[2]M&A Assumptions'!$G$34 -> 50000
A22: Acquirer FD Shares Outstanding | D22: ='[1]M&A Assumptions'!$C$16 -> 50000 | F22: Subordinated Debt | H22: =+OFFSET(I22,0,$H$6-1) -> 0 | I22: ='[2]M&A Assumptions'!$C$35 -> 0 | J22: ='[2]M&A Assumptions'!$D$35 -> 0 | K22: ='[2]M&A Assumptions'!$E$35 -> 0 | L22: ='[2]M&A Assumptions'!$F$35 -> 25000 | M22: ='[2]M&A Assumptions'!$G$35 -> 25000
A23: Target FD Share Outstanding | D23: 25000 | F23: Interest Rate
A24: Shares Issued | D24: =+M38/D28 -> 42757.361 | F24: Senior Debt A | H24: =+OFFSET(I24,0,$H$6-1) -> 0.055 | I24: ='[2]M&A Assumptions'!$C$37 -> 0.055 | J24: ='[2]M&A Assumptions'!$C$37 -> 0.055 | K24: ='[2]M&A Assumptions'!$C$37 -> 0.055 | L24: ='[2]M&A Assumptions'!$C$37 -> 0.055 | M24: ='[2]M&A Assumptions'!$C$37 -> 0.055
A25: Pro Forma Shares Outstanding | D25: =+D22+D24 -> 92757.361 | F25: Senior Debt B | H25: =+OFFSET(I25,0,$H$6-1) -> 0.0575 | I25: ='[2]M&A Assumptions'!$C$38 -> 0.0575 | J25: ='[2]M&A Assumptions'!$C$38 -> 0.0575 | K25: ='[2]M&A Assumptions'!$C$38 -> 0.0575 | L25: ='[2]M&A Assumptions'!$C$38 -> 0.0575 | M25: ='[2]M&A Assumptions'!$C$38 -> 0.0575
F26: Subordinated Debt | H26: =+OFFSET(I26,0,$H$6-1) -> 0.0825 | I26: ='[2]M&A Assumptions'!$C$39 -> 0.0825 | J26: ='[2]M&A Assumptions'!$C$39 -> 0.0825 | K26: ='[2]M&A Assumptions'!$C$39 -> 0.0825 | L26: ='[2]M&A Assumptions'!$C$39 -> 0.0825 | M26: ='[2]M&A Assumptions'!$C$39 -> 0.0825
A27: Share Issuance Discount | D27: ='[2]M&A Assumptions'!$C$19 -> 0.01
A28: Share Issuance Price | D28: =+D8*(1-D27) -> 11.6325
F29: Transaction
F30: Takeover Premium | H30: =+OFFSET(I30,0,$H$6-1) -> 0.15 | I30: ='[2]M&A Assumptions'!$C$42 -> 0.15 | J30: ='[2]M&A Assumptions'!$D$42 -> 0.15 | K30: ='[2]M&A Assumptions'!$E$42 -> 0.2 | L30: ='[2]M&A Assumptions'!$F$42 -> 0.25 | M30: ='[2]M&A Assumptions'!$G$42 -> 0.3
A31: Purchase Price | F31: Cash Consideration | H31: =+OFFSET(I31,0,$H$6-1) -> 0 | I31: ='[2]M&A Assumptions'!$C$43 -> 0 | J31: ='[2]M&A Assumptions'!$D$43 -> 0.2 | K31: ='[2]M&A Assumptions'!$E$43 -> 0.4 | L31: ='[2]M&A Assumptions'!$F$43 -> 0.5 | M31: ='[2]M&A Assumptions'!$G$43 -> 0.55
A32: Target Share Price | D32: =+D9 -> 17.3
A33: Takeover Premium | D33: =+H30 -> 0.15
A34: Offer Price | D34: =+D32*(1+D33) -> 19.895
F35: Sources & Uses of Cash
A36: Acquirer Share Price | D36: =+D8 -> 11.75 | F36: Sources of Cash
A37: Share Exchange Ratio | D37: =+D34/D36 -> 1.6931915 | F37: Cash | I37: =+M44-SUM(I38:I43) -> 46921.25 | K37: Cash Consideration | M37: =+D41*H31 -> 0
F38: Stock Issued | I38: =+M38 -> 497375 | K38: Stock Consideration | M38: =+D41-M37 -> 497375
A39: Target Shares Outstanding | D39: =+D23 -> 25000 | F39: Debt Issued | I39: =+SUM(H20:H22) -> 0 | K39: Target Debt - Replace (ST+LT) | M39: =+IF(D19="Yes", D42,0) -> 0
A40: Offer Price | D40: =+D34 -> 19.895 | K40: Acquirer Debt - Replace (ST+LT) | M40: =+IF(D20="Yes",'Acquirer Model'!O90+'Acquirer Model'!O93,0) -> 30000
A41: Purchase Price | D41: =+D39*D40 -> 497375 | K41: Debt Financing Fees | M41: =+D16*SUM(H20:H22) -> 0
A42: Target Debt (Total Debt ST + LT) | D42: =+'Target Model'!O90+'Target Model'!O93 -> 16801.075 | K42: Equity Financing Fees | M42: =+D15*M38 -> 14921.25
A43: Target Cash | D43: =+'Target Model'!O81 -> 77532.337 | K43: Other Closing Costs | M43: =+D17 -> 2000
A44: Enterprise Value | D44: =+D41+D42-D43 -> 436643.74 | F44: Total Sources | I44: =+SUM(I37:I43) -> 544296.25 | K44: Total Uses | M44: =SUM(M37:M43) -> 544296.25
I45: ^ Total cash needed for transaction | M45: ^ Total cash needed for transaction
A48: Goodwill and Purchase Price Allocation
A49: Fair Market Value | D49: Book Value | E49: Fair Value | F49: Adjustment | I49: Purchase Price Allocation
A50: Inventory & Other Current Assets | D50: =+'Target Model'!O84 -> 78369.435 | F50: =+E50-D50 -> -78369.435 | I50: Total Purchase Price | M50: =+D41 -> 497375
A51: Target PP&E | D51: =+'Target Model'!O85 -> 21786.82 | F51: =+E51-D51 -> -21786.82 | I51: Net Book Value of Assets | M51: =+'Target Model'!O87-'Target Model'!O94 -> 83098.886
A52: Identifiable Intangibles | I52: Excess Purchase Price | M52: =+M50-M51 -> 414276.11
A53: Net Identifiable Assets | D53: =+SUM(D50:D52) -> 100156.25 | E53: =+SUM(E50:E52) -> 0 | F53: =+SUM(F50:F52) -> -100156.25 | I53: Write-off Existing Goodwill | M53: 0
I54: Fair Value Adjustments | M54: =+F53 -> -100156.25
I55: Excess Purchase Price After Adjustments | M55: =+M52-M54 -> 514432.37
I56: Goodwill | M56: =+M55 -> 514432.37 | N56: >> Good will on proforma balance sheet
A59: Closing Balance Sheet
A61: Pro Forma Consolidated Balance Sheet
A62: Step # | D62: 1 | E62: =D62+1 -> 2 | F62: =E62+1 -> 3 | G62: =F62+1 -> 4 | H62: =G62+1 -> 5 | I62: =H62+1 -> 6 | J62: =I62+1 -> 7 | K62: =J62+1 -> 8 | L62: =K62+1 -> 9 | M62: =L62+1 -> 10
D63: Acquirer | E63: Target | F63: Fair Value | G63: Target PF | H63: Purchase | I63: Financing | J63: Financing | K63: Financing | L63: Total Adj. | M63: Consol
D64: =+'Acquirer Model'!O4 -> 45838 | E64: =+'Target Model'!O4 -> 45838 | H64: Transaction | I64: Debt + Equity | J64: Fees | K64: Refi Debt | M64: =+D10 -> 45838
A65: Assets
A66: Cash | D66: =+'Acquirer Model'!O81 -> 147788.27 | E66: =+'Target Model'!O81 -> 77532.337 | G66: =+SUM(E66:F66) -> 77532.337 | H66: =-M37 -> 0 | I66: =+I39 -> 0 | J66: =-SUM(M41:M43) -> -16921.25 | K66: =-SUM(M39:M40) -> -30000 | L66: =+SUM(G66:K66) -> 30611.087 | M66: =+L66+D66 -> 178399.36
A67: Accounts Receivable | D67: =+'Acquirer Model'!O82 -> 8246.6453 | E67: =+'Target Model'!O82 -> 344.22727 | G67: =+SUM(E67:F67) -> 344.22727 | L67: =+SUM(G67:K67) -> 344.22727 | M67: =+L67+D67 -> 8590.8726
A68: Inventory | D68: =+'Acquirer Model'!O83 -> 15393.738 | E68: =+'Target Model'!O83 -> 492.87086 | F68: =+F50 -> -78369.435 | G68: =+SUM(E68:F68) -> -77876.564 | L68: =+SUM(G68:K68) -> -77876.564 | M68: =+L68+D68 -> -62482.826
A69: Current Assets | D69: =SUM(D66:D68) -> 171428.66 | E69: =SUM(E66:E68) -> 78369.435 | L69: =SUM(L66:L68) -> -46921.25 | M69: =SUM(M66:M68) -> 124507.41
A70: Property & Equipment | D70: =+'Acquirer Model'!O85 -> 41268.945 | E70: =+'Target Model'!O85 -> 21786.82 | F70: =+F51 -> -21786.82 | G70: =+SUM(E70:F70) -> 0 | L70: =+SUM(G70:K70) -> 0 | M70: =+L70+D70 -> 41268.945
A71: Goodwill | D71: =+'Acquirer Model'!O86 -> 0 | E71: =+'Target Model'!O86 -> 0 | G71: =+SUM(E71:F71) -> 0 | H71: =+M56 -> 514432.37 | L71: =+SUM(G71:K71) -> 514432.37 | M71: =+L71+D71 -> 514432.37
A72: Total Assets | D72: =+D69+D70+D71 -> 212697.6 | E72: =+E69+E70+E71 -> 100156.25 | L72: =+L69+L70+L71 -> 467511.12 | M72: =+M69+M70+M71 -> 680208.72
A74: Liabilities
A75: Short Term Debt | D75: =+'Acquirer Model'!O90 -> 0
A76: Accounts Payable | D76: =+'Acquirer Model'!O91 -> 7119.6038 | E76: =+'Target Model'!O91 -> 256.29285 | G76: =+SUM(E76:F76) -> 256.29285 | L76: =+SUM(G76:K76) -> 256.29285 | M76: =+L76+D76 -> 7375.8966
A77: Current Liabilities | D77: =SUM(D75:D76) -> 7119.6038 | E77: =SUM(E75:E76) -> 256.29285 | L77: =SUM(L75:L76) -> 256.29285 | M77: =SUM(M75:M76) -> 7375.8966
A78: Long Term Debt | D78: =+'Acquirer Model'!O93 -> 30000 | E78: =+'Target Model'!O93 -> 16801.075 | G78: =+SUM(E78:F78) -> 16801.075 | I78: =+I39 -> 0 | K78: =+K66 -> -30000 | L78: =+SUM(G78:K78) -> -13198.925 | M78: =+L78+D78 -> 16801.075
A79: Total Liabilities | D79: =+D78+D77 -> 37119.604 | E79: =+E78+E77 -> 17057.368 | L79: =+L78+L77 -> -12942.632 | M79: =+M78+M77 -> 24176.972
A80: Shareholder's Equity
A81: Equity Capital | D81: =+'Acquirer Model'!O96 -> 70000 | E81: =+'Target Model'!O96 -> 39202.509 | G81: =+SUM(E81:F81) -> 39202.509 | H81: =-G81 -> -39202.509 | I81: =+I38 -> 497375 | L81: =+SUM(G81:K81) -> 497375 | M81: =+L81+D81 -> 567375
A82: Retained Earnings | D82: =+'Acquirer Model'!O97 -> 105578 | E82: =+'Target Model'!O97 -> 43896.912 | G82: =+SUM(E82:F82) -> 43896.912 | H82: =-G82 -> -43896.912 | J82: =+J66 -> -16921.25 | L82: =+SUM(G82:K82) -> -16921.25 | M82: =+L82+D82 -> 88656.747
A83: Shareholder's Equity | D83: =SUM(D81:D82) -> 175578 | E83: =SUM(E81:E82) -> 83099.421 | L83: =SUM(L81:L82) -> 480453.75 | M83: =SUM(M81:M82) -> 656031.75
A84: Total Liabilities & Shareholder's Equity | D84: =+D83+D79 -> 212697.6 | E84: =+E83+E79 -> 100156.79 | L84: =+L83+L79 -> 467511.12 | M84: =+M83+M79 -> 680208.72
A86: Check | D86: =D84-D72 -> 0 | E86: =E84-E72 -> 0.53459928 | L86: =L84-L72 -> 0 | M86: =M84-M72 -> 0
A89: Accretion/Dilution Analysis
I91: =+'Pro Forma Model'!J2 -> 2026 | J91: =+'Pro Forma Model'!K2 -> 2027 | K91: =+'Pro Forma Model'!L2 -> 2028 | L91: =+'Pro Forma Model'!M2 -> 2029 | M91: =+'Pro Forma Model'!N2 -> 2030
A93: Earnings Per Share
A94: Acquirer Net Earnings | I94: =+'Acquirer Model'!J75 -> 33098.602 | J94: =+'Acquirer Model'!K75 -> 37484.311 | K94: =+'Acquirer Model'!L75 -> 40290.104 | L94: =+'Acquirer Model'!M75 -> 42824.293 | M94: =+'Acquirer Model'!N75 -> 46787.531
A95: Target Net Earnings | I95: =+'Target Model'!J75 -> 23909.776 | J95: =+'Target Model'!K75 -> 28510.13 | K95: =+'Target Model'!L75 -> 32117.516 | L95: =+'Target Model'!M75 -> 35302.79 | M95: =+'Target Model'!N75 -> 38427.94
A96: Pro Forma Net Earnings | I96: =+'Pro Forma Model'!J45 -> 63511.896 | J96: =+'Pro Forma Model'!K45 -> 72662.876 | K96: =+'Pro Forma Model'!L45 -> 80767.99 | L96: =+'Pro Forma Model'!M45 -> 86151.263 | M96: =+'Pro Forma Model'!N45 -> 92373.893
A98: Acquirer Shares O/S | I98: =+$D$22 -> 50000 | J98: =+$D$22 -> 50000 | K98: =+$D$22 -> 50000 | L98: =+$D$22 -> 50000 | M98: =+$D$22 -> 50000
A99: Target Share O/S | I99: =+$D$23 -> 25000 | J99: =+$D$23 -> 25000 | K99: =+$D$23 -> 25000 | L99: =+$D$23 -> 25000 | M99: =+$D$23 -> 25000
A100: Pro Forma Shares O/S | I100: =+$D$25 -> 92757.361 | J100: =+$D$25 -> 92757.361 | K100: =+$D$25 -> 92757.361 | L100: =+$D$25 -> 92757.361 | M100: =+$D$25 -> 92757.361
A102: Acquirer EPS | I102: =+I94/I98 -> 0.66197203 | J102: =+J94/J98 -> 0.74968622 | K102: =+K94/K98 -> 0.80580209 | L102: =+L94/L98 -> 0.85648585 | M102: =+M94/M98 -> 0.93575063
A103: Target EPS | I103: =+I95/I99 -> 0.95639104 | J103: =+J95/J99 -> 1.1404052 | K103: =+K95/K99 -> 1.2847006 | L103: =+L95/L99 -> 1.4121116 | M103: =+M95/M99 -> 1.5371176
A104: Pro Forma EPS | I104: =+I96/I100 -> 0.68471004 | J104: =+J96/J100 -> 0.78336506 | K104: =+K96/K100 -> 0.87074481 | L104: =+L96/L100 -> 0.92878087 | M104: =+M96/M100 -> 0.9958659
A106: Accretion/Dilution | I106: =+I104/I102-1 -> 0.034348898 | J106: =+J104/J102-1 -> 0.044923919 | K106: =+K104/K102-1 -> 0.080593884 | L106: =+L104/L102-1 -> 0.084408891 | M106: =+M104/M102-1 -> 0.064242834
A108: Cash Flow Per Share
A109: Acquirer Cash Flow | I109: =+'Acquirer Model'!J110 -> 38099.324 | J109: =+'Acquirer Model'!K110 -> 42937.72 | K109: =+'Acquirer Model'!L110 -> 48888.281 | L109: =+'Acquirer Model'!M110 -> 52048.228 | M109: =+'Acquirer Model'!N110 -> 57202.843
A110: Target Cash Flow | I110: =+'Target Model'!J110 -> 28274.493 | J110: =+'Target Model'!K110 -> 32190.447 | K110: =+'Target Model'!L110 -> 35998.425 | L110: =+'Target Model'!M110 -> 39408.641 | M110: =+'Target Model'!N110 -> 42879.544
A111: Pro Forma Cash Flow | I111: =+'Pro Forma Model'!J80 -> 66622.897 | J111: =+'Pro Forma Model'!K80 -> 76983.815 | K111: =+'Pro Forma Model'!L80 -> 90278.669 | L111: =+'Pro Forma Model'!M80 -> 97089.764 | M111: =+'Pro Forma Model'!N80 -> 105333.68
A113: Acquirer Shares O/S | I113: =+$D$22 -> 50000 | J113: =+$D$22 -> 50000 | K113: =+$D$22 -> 50000 | L113: =+$D$22 -> 50000 | M113: =+$D$22 -> 50000
A114: Target Share O/S | I114: =+$D$23 -> 25000 | J114: =+$D$23 -> 25000 | K114: =+$D$23 -> 25000 | L114: =+$D$23 -> 25000 | M114: =+$D$23 -> 25000
A115: Pro Forma Shares O/S | I115: =+$D$25 -> 92757.361 | J115: =+$D$25 -> 92757.361 | K115: =+$D$25 -> 92757.361 | L115: =+$D$25 -> 92757.361 | M115: =+$D$25 -> 92757.361
A117: Acquirer CFPS | I117: =+I109/I113 -> 0.76198648 | J117: =+J109/J113 -> 0.85875441 | K117: =+K109/K113 -> 0.97776562 | L117: =+L109/L113 -> 1.0409646 | M117: =+M109/M113 -> 1.1440569
A118: Target CFPS | I118: =+I110/I114 -> 1.1309797 | J118: =+J110/J114 -> 1.2876179 | K118: =+K110/K114 -> 1.439937 | L118: =+L110/L114 -> 1.5763456 | M118: =+M110/M114 -> 1.7151817
A119: Pro Forma CFPS | I119: =+I111/I115 -> 0.71824917 | J119: =+J111/J115 -> 0.82994832 | K119: =+K111/K115 -> 0.97327768 | L119: =+L111/L115 -> 1.0467068 | M119: =+M111/M115 -> 1.135583
A121: Accretion/Dilution | I121: =+I119/I117-1 -> -0.05739907 | J121: =+J119/J117-1 -> -0.033544042 | K121: =+K119/K117-1 -> -0.0045899978 | L121: =+L119/L117-1 -> 0.0055163063 | M121: =+M119/M117-1 -> -0.0074068251
...

Sheet Pro Forma Model
I1: Forecast Period
A2: Pro Forma Model | H2: CLOSE | I2: ='Acquirer Model'!I2 -> 2025 | J2: ='Acquirer Model'!J2 -> 2026 | K2: ='Acquirer Model'!K2 -> 2027 | L2: ='Acquirer Model'!L2 -> 2028 | M2: ='Acquirer Model'!M2 -> 2029 | N2: ='Acquirer Model'!N2 -> 2030
A3: Balance Sheet Check | H3: =IFERROR(IF(ABS(H71)>1,"ERROR","ok"),"ok") -> ok | I3: =IFERROR(IF(ABS(I71)>1,"ERROR","ok"),"ok") -> ok | J3: =IFERROR(IF(ABS(J71)>1,"ERROR","ok"),"ok") -> ok | K3: =IFERROR(IF(ABS(K71)>1,"ERROR","ok"),"ok") -> ok | L3: =IFERROR(IF(ABS(L71)>1,"ERROR","ok"),"ok") -> ok | M3: =IFERROR(IF(ABS(M71)>1,"ERROR","ok"),"ok") -> ok | N3: =IFERROR(IF(ABS(N71)>1,"ERROR","ok"),"ok") -> ok
A4: End of Period | H4: 45838 | I4: 46022 | J4: 46387 | K4: 46752 | L4: 47118 | M4: 47483 | N4: 47848
A5: Days in Period | H5: =I4-H4 -> 184 | I5: =365-H5 -> 181 | J5: 365 | K5: 365 | L5: 366 | M5: 365 | N5: 365
A6: Fraction of Year | H6: 0.5 | I6: 0.5 | J6: 1 | K6: 1 | L6: 1 | M6: 1 | N6: 1
A8: Assumptions
A11: Debt Amortization Schedule | G11: Check
A12: Senior Debt A | G12: =SUM(H12:N12) -> 1 | H12: 0 | I12: 0.25 | J12: 0.25 | K12: 0.25 | L12: 0.25 | M12: 0 | N12: 0
A13: Senior Debt B | G13: =SUM(H13:N13) -> 1 | H13: 0 | I13: 0 | J13: 0.2 | K13: 0.2 | L13: 0.2 | M13: 0.2 | N13: 0.2
A14: Subordinated Debt | G14: =SUM(H14:N14) -> 1 | H14: 0 | I14: 0 | J14: 0 | K14: 0 | L14: 0 | M14: 0 | N14: 1
A17: Revenue Growth (% Change)
A18: Cost of Goods Sold (% of Revenue)
A19: Marketing, Advertising & Promotion (% of Revenue)
A21: Depreciation & Amortization (% of PP&E) | I21: 0.2 | J21: 0.2 | K21: 0.2 | L21: 0.2 | M21: 0.2 | N21: 0.2
A22: Tax Rate (% of Earnings Before Tax) | I22: 0.3 | J22: 0.3 | K22: 0.3 | L22: 0.3 | M22: 0.3 | N22: 0.3
A23: Accounts Receivable (Days) | I23: 18 | J23: 18 | K23: 18 | L23: 18 | M23: 18 | N23: 18
A24: Inventory (Days) | I24: 80 | J24: 90 | K24: 100 | L24: 100 | M24: 100 | N24: 100
A25: Accounts Payable (Days) | I25: 37 | J25: 37 | K25: 37 | L25: 37 | M25: 37 | N25: 37
A27: Equity Issued (Repaid) ($000's) | I27: 0 | J27: 0 | K27: 0 | L27: 0 | M27: 0 | N27: 0
A28: Dividends Paid | I28: 0 | J28: 0 | K28: 0 | L28: 500 | M28: 500 | N28: 500
A31: Income Statement
A33: Revenue | I33: =+I208 -> 131476.29 | J33: =+J208 -> 295753.01 | K33: =+K208 -> 329321.69 | L33: =+L208 -> 361814.58 | M33: =+M208 -> 390319.75 | N33: =+N208 -> 415771.31
A34: Cost of Goods Sold (COGS) | I34: =+I214 -> 55220.042 | J34: =+J214 -> 123968.42 | K34: =+K214 -> 137757.03 | L34: =+L214 -> 152587.76 | M34: =+M214 -> 167227.16 | N34: =+N214 -> 178399.98
A35: Gross Profit | I35: =+I33-I34 -> 76256.249 | J35: =+J33-J34 -> 171784.59 | K35: =+K33-K34 -> 191564.66 | L35: =+L33-L34 -> 209226.82 | M35: =+M33-M34 -> 223092.59 | N35: =+N33-N34 -> 237371.33
A36: Expenses
A37: Marketing, Advertising & Promotion | I37: =+I220 -> 21865.453 | J37: =+J220 -> 48505.823 | K37: =+K220 -> 53313.746 | L37: =+L220 -> 57947.718 | M37: =+M220 -> 62683.536 | N37: =+N220 -> 66921.152
A38: General & Administrative | I38: =+I226 -> 11000 | J38: =+J226 -> 21700 | K38: =+K226 -> 21350 | L38: =+L226 -> 21000 | M38: =+M226 -> 21000 | N38: =+N226 -> 21000
A39: Depreciation & Amortization | I39: =+I111 -> 4126.8945 | J39: =+J111 -> 9503.4101 | K39: =+K111 -> 11752.728 | L39: =+L111 -> 13552.182 | M39: =+M111 -> 14991.746 | N39: =+N111 -> 16143.397
A40: Interest | I40: =+I160 -> 672.04 | J40: =+J160 -> 1344.08 | K40: =+K160 -> 1344.08 | L40: =+L160 -> 1344.08 | M40: =+M160 -> 1344.08 | N40: =+N160 -> 1344.08
A41: Total Expenses | I41: =SUM(I37:I40) -> 37664.387 | J41: =SUM(J37:J40) -> 81053.313 | K41: =SUM(K37:K40) -> 87760.554 | L41: =SUM(L37:L40) -> 93843.981 | M41: =SUM(M37:M40) -> 100019.36 | N41: =SUM(N37:N40) -> 105408.63
A42: Earnings Before Tax | I42: =+I35-I41 -> 38591.862 | J42: =+J35-J41 -> 90731.281 | K42: =+K35-K41 -> 103804.11 | L42: =+L35-L41 -> 115382.84 | M42: =+M35-M41 -> 123073.23 | N42: =+N35-N41 -> 131962.7
A44: Taxes | I44: =+IF(I42>0,I42*I22,0) -> 11577.559 | J44: =+IF(J42>0,J42*J22,0) -> 27219.384 | K44: =+IF(K42>0,K42*K22,0) -> 31141.233 | L44: =+IF(L42>0,L42*L22,0) -> 34614.853 | M44: =+IF(M42>0,M42*M22,0) -> 36921.97 | N44: =+IF(N42>0,N42*N22,0) -> 39588.811
A45: Net Earnings | I45: =+I42-I44 -> 27014.303 | J45: =+J42-J44 -> 63511.896 | K45: =+K42-K44 -> 72662.876 | L45: =+L42-L44 -> 80767.99 | M45: =+M42-M44 -> 86151.263 | N45: =+N42-N44 -> 92373.893
A48: Balance Sheet
A50: Assets
A51: Cash | H51: =+'M&A Assumptions & Analysis'!M66 -> 178399.36 | I51: =+I95 -> 111704.14 | J51: =+J95 -> 157577.04 | K51: =+K95 -> 213810.86 | L51: =+L95 -> 282839.52 | M51: =+M95 -> 358679.29 | N51: =+N95 -> 432762.97
A52: Accounts Receivable | H52: =+'M&A Assumptions & Analysis'!M67 -> 8590.8726 | I52: =+I33*I23/I5 -> 13074.99 | J52: =+J33*J23/J5 -> 14585.08 | K52: =+K33*K23/K5 -> 16240.522 | L52: =+L33*L23/L5 -> 17794.16 | M52: =+M33*M23/M5 -> 19248.645 | N52: =+N33*N23/N5 -> 20503.791
A53: Inventory | H53: =+'M&A Assumptions & Analysis'!M68 -> -62482.826 | I53: =+I34*I24/I5 -> 24406.649 | J53: =+J34*J24/J5 -> 30567.555 | K53: =+K34*K24/K5 -> 37741.651 | L53: =+L34*L24/L5 -> 41690.644 | M53: =+M34*M24/M5 -> 45815.659 | N53: =+N34*N24/N5 -> 48876.706
A54: Current Assets | H54: =SUM(H51:H53) -> 124507.41 | I54: =SUM(I51:I53) -> 149185.78 | J54: =SUM(J51:J53) -> 202729.67 | K54: =SUM(K51:K53) -> 267793.03 | L54: =SUM(L51:L53) -> 342324.33 | M54: =SUM(M51:M53) -> 423743.59 | N54: =SUM(N51:N53) -> 502143.47
A55: Property & Equipment | H55: =+'M&A Assumptions & Analysis'!M70 -> 41268.945 | I55: =+I112 -> 47517.05 | J55: =+J112 -> 58763.64 | K55: =+K112 -> 67760.912 | L55: =+L112 -> 74958.73 | M55: =+M112 -> 80716.984 | N55: =+N112 -> 85323.587
A56: Goodwill | H56: =+'M&A Assumptions & Analysis'!M71 -> 514432.37 | I56: =+H56 -> 514432.37 | J56: =+I56 -> 514432.37 | K56: =+J56 -> 514432.37 | L56: =+K56 -> 514432.37 | M56: =+L56 -> 514432.37 | N56: =+M56 -> 514432.37
A57: Total Assets | H57: =+SUM(H54:H56) -> 680208.72 | I57: =+SUM(I54:I56) -> 711135.2 | J57: =+SUM(J54:J56) -> 775925.68 | K57: =+SUM(K54:K56) -> 849986.31 | L57: =+SUM(L54:L56) -> 931715.43 | M57: =+SUM(M54:M56) -> 1018892.9 | N57: =+SUM(N54:N56) -> 1101899.4
A59: Liabilities
A60: Short Term Debt
A61: Accounts Payable | H61: =+'M&A Assumptions & Analysis'!M76 -> 7375.8966 | I61: =+I34*I25/I5 -> 11288.075 | J61: =+J34*J25/J5 -> 12566.661 | K61: =+K34*K25/K5 -> 13964.411 | L61: =+L34*L25/L5 -> 15425.538 | M61: =+M34*M25/M5 -> 16951.794 | N61: =+N34*N25/N5 -> 18084.381
A62: Current Liabilities | H62: =SUM(H60:H61) -> 7375.8966 | I62: =SUM(I60:I61) -> 11288.075 | J62: =SUM(J60:J61) -> 12566.661 | K62: =SUM(K60:K61) -> 13964.411 | L62: =SUM(L60:L61) -> 15425.538 | M62: =SUM(M60:M61) -> 16951.794 | N62: =SUM(N60:N61) -> 18084.381
A63: Long Term Debt | H63: =+'M&A Assumptions & Analysis'!M78 -> 16801.075 | I63: =+I143 -> 16801 | J63: =+J143 -> 16801 | K63: =+K143 -> 16801 | L63: =+L143 -> 16801 | M63: =+M143 -> 16801 | N63: =+N143 -> 6801
A64: Total Liabilities | H64: =+H62+H63 -> 24176.972 | I64: =+I62+I63 -> 28089.075 | J64: =+J62+J63 -> 29367.661 | K64: =+K62+K63 -> 30765.411 | L64: =+L62+L63 -> 32226.538 | M64: =+M62+M63 -> 33752.794 | N64: =+N62+N63 -> 24885.381
A65: Shareholder's Equity
A66: Equity Capital | H66: =+'M&A Assumptions & Analysis'!M81 -> 567375 | I66: =+H66+I27 -> 567375 | J66: =+I66+J27 -> 567375 | K66: =+J66+K27 -> 567375 | L66: =+K66+L27 -> 567375 | M66: =+L66+M27 -> 567375 | N66: =+M66+N27 -> 567375
A67: Retained Earnings | H67: =+'M&A Assumptions & Analysis'!M82 -> 88656.747 | I67: =+H67+I45-I28 -> 115671.05 | J67: =+I67+J45-J28 -> 179182.95 | K67: =+J67+K45-K28 -> 251845.82 | L67: =+K67+L45-L28 -> 332113.81 | M67: =+L67+M45-M28 -> 417765.08 | N67: =+M67+N45-N28 -> 509638.97
A68: Shareholder's Equity | H68: =SUM(H66:H67) -> 656031.75 | I68: =SUM(I66:I67) -> 683046.05 | J68: =SUM(J66:J67) -> 746557.95 | K68: =SUM(K66:K67) -> 819220.82 | L68: =SUM(L66:L67) -> 899488.81 | M68: =SUM(M66:M67) -> 985140.08 | N68: =SUM(N66:N67) -> 1077014
A69: Total Liabilities & Shareholder's Equity | H69: =+H64+H68 -> 680208.72 | I69: =+I64+I68 -> 711135.12 | J69: =+J64+J68 -> 775925.61 | K69: =+K64+K68 -> 849986.23 | L69: =+L64+L68 -> 931715.35 | M69: =+M64+M68 -> 1018892.9 | N69: =+N64+N68 -> 1101899.3
A71: Check | H71: =H69-H57 -> 0 | I71: =I69-I57 -> -0.075268817 | J71: =J69-J57 -> -0.075268817 | K71: =K69-K57 -> -0.075268817 | L71: =L69-L57 -> -0.075268817 | M71: =M69-M57 -> -0.075268817 | N71: =N69-N57 -> -0.075268817
A74: Cash Flow Statement
A76: Operating Cash Flow
A77: Net Earnings | I77: =+I45 -> 27014.303 | J77: =+J45 -> 63511.896 | K77: =+K45 -> 72662.876 | L77: =+L45 -> 80767.99 | M77: =+M45 -> 86151.263 | N77: =+N45 -> 92373.893
A78: Plus: Depreciation & Amortization | I78: =+I39 -> 4126.8945 | J78: =+J39 -> 9503.4101 | K78: =+K39 -> 11752.728 | L78: =+L39 -> 13552.182 | M78: =+M39 -> 14991.746 | N78: =+N39 -> 16143.397
A79: Less: Changes in Working Capital | I79: =-I106 -> -87461.414 | J79: =-J106 -> -6392.4094 | K79: =-K106 -> -7431.7886 | L79: =-L106 -> -4041.5039 | M79: =-M106 -> -4053.2445 | N79: =-N106 -> -3183.6052
A80: Cash from Operations | I80: =SUM(I77:I79) -> -56320.216 | J80: =SUM(J77:J79) -> 66622.897 | K80: =SUM(K77:K79) -> 76983.815 | L80: =SUM(L77:L79) -> 90278.669 | M80: =SUM(M77:M79) -> 97089.764 | N80: =SUM(N77:N79) -> 105333.68
A82: Investing Cash Flow
A83: Investments in Property & Equipment | I83: =-I110 -> -10375 | J83: =-J110 -> -20750 | K83: =-K110 -> -20750 | L83: =-L110 -> -20750 | M83: =-M110 -> -20750 | N83: =-N110 -> -20750
A84: Investments in Businesses
A85: Cash from Investing | I85: =SUM(I83:I84) -> -10375 | J85: =SUM(J83:J84) -> -20750 | K85: =SUM(K83:K84) -> -20750 | L85: =SUM(L83:L84) -> -20750 | M85: =SUM(M83:M84) -> -20750 | N85: =SUM(N83:N84) -> -20750
A87: Financing Cash Flow
A88: Issuance (repayment) of debt | I88: =I142 -> 0 | J88: =J142 -> 0 | K88: =K142 -> 0 | L88: =L142 -> 0 | M88: =M142 -> 0 | N88: =N142 -> -10000
A89: Issuance (repayment) of equity | I89: =+I27 -> 0 | J89: =+J27 -> 0 | K89: =+K27 -> 0 | L89: =+L27 -> 0 | M89: =+M27 -> 0 | N89: =+N27 -> 0
A90: Payment of Dividends | I90: =-I28 -> 0 | J90: =-J28 -> 0 | K90: =-K28 -> 0 | L90: =-L28 -> -500 | M90: =-M28 -> -500 | N90: =-N28 -> -500
A91: Cash from Financing | I91: =SUM(I88:I90) -> 0 | J91: =SUM(J88:J90) -> 0 | K91: =SUM(K88:K90) -> 0 | L91: =SUM(L88:L90) -> -500 | M91: =SUM(M88:M90) -> -500 | N91: =SUM(N88:N90) -> -10500
A93: Net Increase (decrease) in Cash | I93: =+I80+I85+I91 -> -66695.216 | J93: =+J80+J85+J91 -> 45872.897 | K93: =+K80+K85+K91 -> 56233.815 | L93: =+L80+L85+L91 -> 69028.669 | M93: =+M80+M85+M91 -> 75839.764 | N93: =+N80+N85+N91 -> 74083.684
A94: Opening Cash Balance | I94: =+H95 -> 178399.36 | J94: =+I95 -> 111704.14 | K94: =+J95 -> 157577.04 | L94: =+K95 -> 213810.86 | M94: =+L95 -> 282839.52 | N94: =+M95 -> 358679.29
A95: Closing Cash Balance | H95: =+H51 -> 178399.36 | I95: =SUM(I93:I94) -> 111704.14 | J95: =SUM(J93:J94) -> 157577.04 | K95: =SUM(K93:K94) -> 213810.86 | L95: =SUM(L93:L94) -> 282839.52 | M95: =SUM(M93:M94) -> 358679.29 | N95: =SUM(N93:N94) -> 432762.97
A99: Supporting Schedules
A101: Working Capital Schedule
A102: Accounts Receivable | H102: =+H52 -> 8590.8726 | I102: =+I52 -> 13074.99 | J102: =+J52 -> 14585.08 | K102: =+K52 -> 16240.522 | L102: =+L52 -> 17794.16 | M102: =+M52 -> 19248.645 | N102: =+N52 -> 20503.791
A103: Inventory | H103: =+H53 -> -62482.826 | I103: =+I53 -> 24406.649 | J103: =+J53 -> 30567.555 | K103: =+K53 -> 37741.651 | L103: =+L53 -> 41690.644 | M103: =+M53 -> 45815.659 | N103: =+N53 -> 48876.706
A104: Accounts Payable | H104: =+H61 -> 7375.8966 | I104: =+I61 -> 11288.075 | J104: =+J61 -> 12566.661 | K104: =+K61 -> 13964.411 | L104: =+L61 -> 15425.538 | M104: =+M61 -> 16951.794 | N104: =+N61 -> 18084.381
A105: Net Working Capital (NWC) | H105: =+H102+H103-H104 -> -61267.85 | I105: =+I102+I103-I104 -> 26193.564 | J105: =+J102+J103-J104 -> 32585.973 | K105: =+K102+K103-K104 -> 40017.762 | L105: =+L102+L103-L104 -> 44059.266 | M105: =+M102+M103-M104 -> 48112.51 | N105: =+N102+N103-N104 -> 51296.115
A106: Change in NWC | I106: =+I105-H105 -> 87461.414 | J106: =+J105-I105 -> 6392.4094 | K106: =+K105-J105 -> 7431.7886 | L106: =+L105-K105 -> 4041.5039 | M106: =+M105-L105 -> 4053.2445 | N106: =+N105-M105 -> 3183.6052
A108: Depreciation Schedule
A109: PPE Opening | I109: =+H112 -> 41268.945 | J109: =+I112 -> 47517.05 | K109: =+J112 -> 58763.64 | L109: =+K112 -> 67760.912 | M109: =+L112 -> 74958.73 | N109: =+M112 -> 80716.984
A110: Plus Capex | I110: =+('Acquirer Model'!I140+'Target Model'!I140)*I6 -> 10375 | J110: =+('Acquirer Model'!J140+'Target Model'!J140)*J6 -> 20750 | K110: =+('Acquirer Model'!K140+'Target Model'!K140)*K6 -> 20750 | L110: =+('Acquirer Model'!L140+'Target Model'!L140)*L6 -> 20750 | M110: =+('Acquirer Model'!M140+'Target Model'!M140)*M6 -> 20750 | N110: =+('Acquirer Model'!N140+'Target Model'!N140)*N6 -> 20750
A111: Less Depreciation | I111: =+I109*I21*I6 -> 4126.8945 | J111: =+J109*J21*J6 -> 9503.4101 | K111: =+K109*K21*K6 -> 11752.728 | L111: =+L109*L21*L6 -> 13552.182 | M111: =+M109*M21*M6 -> 14991.746 | N111: =+N109*N21*N6 -> 16143.397
A112: PPE Closing | H112: =+H55 -> 41268.945 | I112: =+I109+I110-I111 -> 47517.05 | J112: =+J109+J110-J111 -> 58763.64 | K112: =+K109+K110-K111 -> 67760.912 | L112: =+L109+L110-L111 -> 74958.73 | M112: =+M109+M110-M111 -> 80716.984 | N112: =+N109+N110-N111 -> 85323.587
A114: Debt Schedule
A115: Senior Debt A
A116: Opening Balance | I116: =+H118 -> 0 | J116: =+I118 -> 0 | K116: =+J118 -> 0 | L116: =+K118 -> 0 | M116: =+L118 -> 0 | N116: =+M118 -> 0
A117: Addition (Repayment) | I117: =-$H$118*I12 -> 0 | J117: =-$H$118*J12 -> 0 | K117: =-$H$118*K12 -> 0 | L117: =-$H$118*L12 -> 0 | M117: =-$H$118*M12 -> 0 | N117: =-$H$118*N12 -> 0
A118: Closing Balance | H118: =+'M&A Assumptions & Analysis'!H20 -> 0 | I118: =SUM(I116:I117) -> 0 | J118: =SUM(J116:J117) -> 0 | K118: =SUM(K116:K117) -> 0 | L118: =SUM(L116:L117) -> 0 | M118: =SUM(M116:M117) -> 0 | N118: =SUM(N116:N117) -> 0
A120: Senior Debt B
A121: Opening Balance | I121: =+H123 -> 0 | J121: =+I123 -> 0 | K121: =+J123 -> 0 | L121: =+K123 -> 0 | M121: =+L123 -> 0 | N121: =+M123 -> 0
A122: Addition (Repayment) | I122: =-$H$123*I13 -> 0 | J122: =-$H$123*J13 -> 0 | K122: =-$H$123*K13 -> 0 | L122: =-$H$123*L13 -> 0 | M122: =-$H$123*M13 -> 0 | N122: =-$H$123*N13 -> 0
A123: Closing Balance | H123: =+'M&A Assumptions & Analysis'!H21 -> 0 | I123: =SUM(I121:I122) -> 0 | J123: =SUM(J121:J122) -> 0 | K123: =SUM(K121:K122) -> 0 | L123: =SUM(L121:L122) -> 0 | M123: =SUM(M121:M122) -> 0 | N123: =SUM(N121:N122) -> 0
A125: Subordinated Debt
A126: Opening Balance | I126: =+H128 -> 0 | J126: =+I128 -> 0 | K126: =+J128 -> 0 | L126: =+K128 -> 0 | M126: =+L128 -> 0 | N126: =+M128 -> 0
A127: Addition (Repayment) | I127: =-$H$128*I14 -> 0 | J127: =-$H$128*J14 -> 0 | K127: =-$H$128*K14 -> 0 | L127: =-$H$128*L14 -> 0 | M127: =-$H$128*M14 -> 0 | N127: =-$H$128*N14 -> 0
A128: Closing Balance | H128: =+'M&A Assumptions & Analysis'!H22 -> 0 | I128: =SUM(I126:I127) -> 0 | J128: =SUM(J126:J127) -> 0 | K128: =SUM(K126:K127) -> 0 | L128: =SUM(L126:L127) -> 0 | M128: =SUM(M126:M127) -> 0 | N128: =SUM(N126:N127) -> 0
A130: Target Debt
A131: Opening Balance | I131: =+H133 -> 16801 | J131: =+I133 -> 16801 | K131: =+J133 -> 16801 | L131: =+K133 -> 16801 | M131: =+L133 -> 16801 | N131: =+M133 -> 16801
...

Sheet Acquirer Model
D1: Historical Results | I1: Forecast Period | O1: Stub
A2: ='M&A Assumptions & Analysis'!D6& " Model" -> Online Company Inc Model | D2: 2020 | E2: =+D2+1 -> 2021 | F2: =+E2+1 -> 2022 | G2: =+F2+1 -> 2023 | H2: =+G2+1 -> 2024 | I2: =+H2+1 -> 2025 | J2: =+I2+1 -> 2026 | K2: =+J2+1 -> 2027 | L2: =+K2+1 -> 2028 | ... N2: =+M2+1 -> 2030 | O2: =+O4 -> 45838 | P2: =+P4 -> 46022
A3: Balance Sheet Check | D3: =IFERROR(IF(ABS(D101)>1,"ERROR","ok"),"ok") -> ok | E3: =IFERROR(IF(ABS(E101)>1,"ERROR","ok"),"ok") -> ok | F3: =IFERROR(IF(ABS(F101)>1,"ERROR","ok"),"ok") -> ok | G3: =IFERROR(IF(ABS(G101)>1,"ERROR","ok"),"ok") -> ok | H3: =IFERROR(IF(ABS(H101)>1,"ERROR","ok"),"ok") -> ok | I3: =IFERROR(IF(ABS(I101)>1,"ERROR","ok"),"ok") -> ok | J3: =IFERROR(IF(ABS(J101)>1,"ERROR","ok"),"ok") -> ok | K3: =IFERROR(IF(ABS(K101)>1,"ERROR","ok"),"ok") -> ok | ... N3: =IFERROR(IF(ABS(N101)>1,"ERROR","ok"),"ok") -> ok
A4: End of Period | D4: 44196 | E4: =EOMONTH(D4,12) -> 44561 | F4: =EOMONTH(E4,12) -> 44926 | G4: =EOMONTH(F4,12) -> 45291 | H4: =EOMONTH(G4,12) -> 45657 | I4: =EOMONTH(H4,12) -> 46022 | J4: =EOMONTH(I4,12) -> 46387 | K4: =EOMONTH(J4,12) -> 46752 | L4: =EOMONTH(K4,12) -> 47118 | ... N4: =EOMONTH(M4,12) -> 47848 | O4: =+'M&A Assumptions & Analysis'!D10 -> 45838 | P4: =+EOMONTH(O4,P6*12) -> 46022
A5: Days in Period | D5: 366 | E5: =E4-D4 -> 365 | F5: =F4-E4 -> 365 | G5: =G4-F4 -> 365 | H5: =H4-G4 -> 366 | I5: =I4-H4 -> 365 | J5: =J4-I4 -> 365 | K5: =K4-J4 -> 365 | L5: =L4-K4 -> 366 | ... N5: =N4-M4 -> 365 | O5: =+O4-H4 -> 181 | P5: =+P4-O4 -> 184
A6: Fraction of Year | D6: 1 | E6: =D6 -> 1 | F6: =E6 -> 1 | G6: =F6 -> 1 | H6: =G6 -> 1 | I6: =H6 -> 1 | J6: =I6 -> 1 | K6: =J6 -> 1 | L6: =K6 -> 1 | ... N6: =M6 -> 1 | O6: 0.5 | P6: =1-O6 -> 0.5
A8: Assumptions
H10: LIVE SCENARIO | I10: 1
A12: SCENARIO 1
A13: Revenue Growth (% Change) | I13: 0.1 | J13: 0.1 | K13: 0.1 | L13: 0.09 | M13: 0.08 | N13: 0.07 | O13: 0.1 | P13: 0.1
A14: Cost of Goods Sold (% of Revenue) | D14: 0.37 | E14: 0.38 | F14: 0.39 | G14: 0.4 | H14: 0.41 | I14: 0.42 | J14: 0.43 | K14: 0.44 | L14: 0.45 | M14: 0.46 | N14: 0.46 | O14: 0.42 | P14: 0.42
A15: Salaries and Benefits (% of Revenue) | I15: 0.17 | J15: 0.17 | K15: 0.17 | L15: 0.17 | M15: 0.17 | N15: 0.17 | O15: 0.17 | P15: 0.17
A16: Rent and Overhead ($000's) | I16: 15000 | J16: 15000 | K16: 15000 | L16: 15000 | M16: 15000 | N16: 15000 | O16: 15000 | P16: 15000
A17: Depreciation & Amortization (% of PP&E) | I17: 0.2 | J17: 0.2 | K17: 0.2 | L17: 0.2 | M17: 0.2 | N17: 0.2 | O17: 0.2 | P17: 0.2
A18: Interest (% of Debt) | I18: 0.1 | J18: 0.1 | K18: 0.1 | L18: 0.1 | M18: 0.1 | N18: 0.1 | O18: 0.1 | P18: 0.1
A19: Tax Rate (% of Earnings Before Tax) | I19: 0.28 | J19: 0.28 | K19: 0.28 | L19: 0.28 | M19: 0.28 | N19: 0.28 | O19: 0.28 | P19: 0.28
A20: Accounts Receivable (Days) | I20: 18 | J20: 18 | K20: 18 | L20: 18 | M20: 18 | N20: 18 | O20: 18 | P20: 18
A21: Inventory (Days) | I21: 80 | J21: 90 | K21: 100 | L21: 100 | M21: 100 | N21: 100 | O21: 80 | P21: 80
A22: Accounts Payable (Days) | I22: 37 | J22: 37 | K22: 37 | L22: 37 | M22: 37 | N22: 37 | O22: 37 | P22: 37
A23: Capital Expenditures ($000's) | D23: 15000 | E23: 15000 | F23: 15000 | G23: 15000 | H23: 15000 | I23: 15000 | J23: 15000 | K23: 15000 | L23: 15000 | M23: 15000 | N23: 15000 | O23: 15000 | P23: 15000
A24: Debt Issuance (Repayment) ($000's) | I24: 0 | J24: 0 | K24: -20000 | L24: 0 | M24: 0 | N24: 0 | O24: 0 | P24: 0
A25: Equity Issued (Repaid) ($000's) | I25: 0 | J25: 0 | K25: 0 | L25: 0 | M25: 0 | N25: 0 | O25: 0 | P25: 0
A26: Payment of Dividends | I26: 0 | J26: 0 | K26: 0 | L26: 0 | M26: 200 | N26: 200 | O26: 0 | P26: 0
A28: SCENARIO 2
A29: Revenue Growth (% Change) | I29: 0.05 | J29: 0.045 | K29: 0.04 | L29: 0.035 | M29: 0.03 | N29: 0.03 | O29: 0.05 | P29: 0.05
A30: Cost of Goods Sold (% of Revenue) | I30: 0.37 | J30: 0.37 | K30: 0.36 | L30: 0.36 | M30: 0.35 | N30: 0.35 | O30: 0.37 | P30: 0.37
A31: Salaries and Benefits (% of Revenue) | I31: 0.17 | J31: 0.17 | K31: 0.17 | L31: 0.17 | M31: 0.17 | N31: 0.17 | O31: 0.17 | P31: 0.17
A32: Rent and Overhead ($000's) | I32: 10000 | J32: 10000 | K32: 10000 | L32: 10000 | M32: 10000 | N32: 10000 | O32: 10000 | P32: 10000
A33: Depreciation & Amortization (% of PP&E) | I33: 0.2 | J33: 0.2 | K33: 0.2 | L33: 0.2 | M33: 0.2 | N33: 0.2 | O33: 0.2 | P33: 0.2
A34: Interest (% of Debt) | I34: 0.05 | J34: 0.05 | K34: 0.05 | L34: 0.05 | M34: 0.05 | N34: 0.05 | O34: 0.05 | P34: 0.05
A35: Tax Rate (% of Earnings Before Tax) | I35: 0.28 | J35: 0.28 | K35: 0.28 | L35: 0.28 | M35: 0.28 | N35: 0.28 | O35: 0.28 | P35: 0.28
A36: Accounts Receivable (Days) | I36: 18 | J36: 18 | K36: 18 | L36: 18 | M36: 18 | N36: 18 | O36: 18 | P36: 18
A37: Inventory (Days) | I37: 73 | J37: 73 | K37: 73 | L37: 73 | M37: 73 | N37: 73 | O37: 73 | P37: 73
A38: Accounts Payable (Days) | I38: 37 | J38: 37 | K38: 37 | L38: 37 | M38: 37 | N38: 37 | O38: 37 | P38: 37
A39: Capital Expenditures ($000's) | I39: 15000 | J39: 15000 | K39: 15000 | L39: 15000 | M39: 15000 | N39: 15000 | O39: 15000 | P39: 15000
A40: Debt Issuance (Repayment) ($000's) | I40: 0 | J40: 0 | K40: -20000 | L40: 0 | M40: 0 | N40: 0 | O40: 0 | P40: 0
... A42: Payment of Dividends | I42: 0 | J42: 0 | K42: 0 | L42: 0 | M42: 100 | N42: 100 | O42: 0 | P42: 0
A44: LIVE SCENARIO
A45: Revenue Growth (% Change) | I45: =CHOOSE($I$10,I13,I29) -> 0.1 | J45: =CHOOSE($I$10,J13,J29) -> 0.1 | K45: =CHOOSE($I$10,K13,K29) -> 0.1 | L45: =CHOOSE($I$10,L13,L29) -> 0.09 | M45: =CHOOSE($I$10,M13,M29) -> 0.08 | N45: =CHOOSE($I$10,N13,N29) -> 0.07 | O45: =CHOOSE($I$10,O13,O29) -> 0.1 | P45: =CHOOSE($I$10,P13,P29) -> 0.1
A46: Cost of Goods Sold (% of Revenue) | D46: =D14 -> 0.37 | E46: =E14 -> 0.38 | F46: =F14 -> 0.39 | G46: =G14 -> 0.4 | H46: =H14 -> 0.41 | I46: =CHOOSE($I$10,I14,I30) -> 0.42 | J46: =CHOOSE($I$10,J14,J30) -> 0.43 | K46: =CHOOSE($I$10,K14,K30) -> 0.44 | L46: =CHOOSE($I$10,L14,L30) -> 0.45 | M46: =CHOOSE($I$10,M14,M30) -> 0.46 | N46: =CHOOSE($I$10,N14,N30) -> 0.46 | O46: =CHOOSE($I$10,O14,O30) -> 0.42 | P46: =CHOOSE($I$10,P14,P30) -> 0.42
A47: Marketing, Advertising & Promotion (% of Revenue) | I47: =CHOOSE($I$10,I15,I31) -> 0.17 | J47: =CHOOSE($I$10,J15,J31) -> 0.17 | K47: =CHOOSE($I$10,K15,K31) -> 0.17 | L47: =CHOOSE($I$10,L15,L31) -> 0.17 | M47: =CHOOSE($I$10,M15,M31) -> 0.17 | N47: =CHOOSE($I$10,N15,N31) -> 0.17 | O47: =CHOOSE($I$10,O15,O31) -> 0.17 | P47: =CHOOSE($I$10,P15,P31) -> 0.17
A48: General & Administrative ($000's) | I48: =CHOOSE($I$10,I16,I32) -> 15000 | J48: =CHOOSE($I$10,J16,J32) -> 15000 | K48: =CHOOSE($I$10,K16,K32) -> 15000 | L48: =CHOOSE($I$10,L16,L32) -> 15000 | M48: =CHOOSE($I$10,M16,M32) -> 15000 | N48: =CHOOSE($I$10,N16,N32) -> 15000 | O48: =CHOOSE($I$10,O16,O32) -> 15000 | P48: =CHOOSE($I$10,P16,P32) -> 15000
A49: Depreciation & Amortization (% of PP&E) | D49: 0.2 | E49: 0.2 | F49: 0.2 | G49: 0.2 | H49: 0.2 | I49: =CHOOSE($I$10,I17,I33) -> 0.2 | J49: =CHOOSE($I$10,J17,J33) -> 0.2 | K49: =CHOOSE($I$10,K17,K33) -> 0.2 | L49: =CHOOSE($I$10,L17,L33) -> 0.2 | M49: =CHOOSE($I$10,M17,M33) -> 0.2 | N49: =CHOOSE($I$10,N17,N33) -> 0.2 | O49: =CHOOSE($I$10,O17,O33) -> 0.2 | P49: =CHOOSE($I$10,P17,P33) -> 0.2
A50: Interest (% of Debt) | I50: =CHOOSE($I$10,I18,I34) -> 0.1 | J50: =CHOOSE($I$10,J18,J34) -> 0.1 | K50: =CHOOSE($I$10,K18,K34) -> 0.1 | L50: =CHOOSE($I$10,L18,L34) -> 0.1 | M50: =CHOOSE($I$10,M18,M34) -> 0.1 | N50: =CHOOSE($I$10,N18,N34) -> 0.1 | O50: =CHOOSE($I$10,O18,O34) -> 0.1 | P50: =CHOOSE($I$10,P18,P34) -> 0.1
A51: Tax Rate (% of Earnings Before Tax) | I51: =CHOOSE($I$10,I19,I35) -> 0.28 | J51: =CHOOSE($I$10,J19,J35) -> 0.28 | K51: =CHOOSE($I$10,K19,K35) -> 0.28 | L51: =CHOOSE($I$10,L19,L35) -> 0.28 | M51: =CHOOSE($I$10,M19,M35) -> 0.28 | N51: =CHOOSE($I$10,N19,N35) -> 0.28 | O51: =CHOOSE($I$10,O19,O35) -> 0.28 | P51: =CHOOSE($I$10,P19,P35) -> 0.28
A52: Accounts Receivable (Days) | D52: 18 | E52: 18 | F52: 18 | G52: 18 | H52: 18 | I52: =CHOOSE($I$10,I20,I36) -> 18 | J52: =CHOOSE($I$10,J20,J36) -> 18 | K52: =CHOOSE($I$10,K20,K36) -> 18 | L52: =CHOOSE($I$10,L20,L36) -> 18 | M52: =CHOOSE($I$10,M20,M36) -> 18 | N52: =CHOOSE($I$10,N20,N36) -> 18 | O52: =CHOOSE($I$10,O20,O36) -> 18 | P52: =CHOOSE($I$10,P20,P36) -> 18
A53: Inventory (Days) | D53: 30 | E53: 40 | F53: 40 | G53: 50 | H53: 50 | I53: =CHOOSE($I$10,I21,I37) -> 80 | J53: =CHOOSE($I$10,J21,J37) -> 90 | K53: =CHOOSE($I$10,K21,K37) -> 100 | L53: =CHOOSE($I$10,L21,L37) -> 100 | M53: =CHOOSE($I$10,M21,M37) -> 100 | N53: =CHOOSE($I$10,N21,N37) -> 100 | O53: =CHOOSE($I$10,O21,O37) -> 80 | P53: =CHOOSE($I$10,P21,P37) -> 80
A54: Accounts Payable (Days) | D54: 37 | E54: 37 | F54: 37 | G54: 37 | H54: 37 | I54: =CHOOSE($I$10,I22,I38) -> 37 | J54: =CHOOSE($I$10,J22,J38) -> 37 | K54: =CHOOSE($I$10,K22,K38) -> 37 | L54: =CHOOSE($I$10,L22,L38) -> 37 | M54: =CHOOSE($I$10,M22,M38) -> 37 | N54: =CHOOSE($I$10,N22,N38) -> 37 | O54: =CHOOSE($I$10,O22,O38) -> 37 | P54: =CHOOSE($I$10,P22,P38) -> 37
A55: Capital Expenditures ($000's) | D55: 15000 | E55: 15000 | F55: 15000 | G55: 15000 | H55: 15000 | I55: =CHOOSE($I$10,I23,I39) -> 15000 | J55: =CHOOSE($I$10,J23,J39) -> 15000 | K55: =CHOOSE($I$10,K23,K39) -> 15000 | L55: =CHOOSE($I$10,L23,L39) -> 15000 | M55: =CHOOSE($I$10,M23,M39) -> 15000 | N55: =CHOOSE($I$10,N23,N39) -> 15000 | O55: =CHOOSE($I$10,O23,O39) -> 15000 | P55: =CHOOSE($I$10,P23,P39) -> 15000
A56: Debt Issuance (Repayment) ($000's) | I56: =CHOOSE($I$10,I24,I40) -> 0 | J56: =CHOOSE($I$10,J24,J40) -> 0 | K56: =CHOOSE($I$10,K24,K40) -> -20000 | L56: =CHOOSE($I$10,L24,L40) -> 0 | M56: =CHOOSE($I$10,M24,M40) -> 0 | N56: =CHOOSE($I$10,N24,N40) -> 0 | O56: =CHOOSE($I$10,O24,O40) -> 0 | P56: =CHOOSE($I$10,P24,P40) -> 0
A57: Equity Issued (Repaid) ($000's) | I57: =CHOOSE($I$10,I25,I41) -> 0 | J57: =CHOOSE($I$10,J25,J41) -> 0 | K57: =CHOOSE($I$10,K25,K41) -> 0 | L57: =CHOOSE($I$10,L25,L41) -> 0 | M57: =CHOOSE($I$10,M25,M41) -> 0 | N57: =CHOOSE($I$10,N25,N41) -> 0 | O57: =CHOOSE($I$10,O25,O41) -> 0 | P57: =CHOOSE($I$10,P25,P41) -> 0
A58: Payment of Dividends | I58: =CHOOSE($I$10,I26,I42) -> 0 | J58: =CHOOSE($I$10,J26,J42) -> 0 | K58: =CHOOSE($I$10,K26,K42) -> 0 | L58: =CHOOSE($I$10,L26,L42) -> 0 | M58: =CHOOSE($I$10,M26,M42) -> 200 | N58: =CHOOSE($I$10,N26,N42) -> 200 | O58: =CHOOSE($I$10,O26,O42) -> 0 | P58: =CHOOSE($I$10,P26,P42) -> 0
A61: Income Statement
A63: Revenue | D63: 102007 | E63: 118086 | F63: 131345 | G63: 142341 | H63: 150772 | I63: =H63*((1+I45)) -> 165849.2 | J63: =I63*((1+J45)) -> 182434.12 | K63: =J63*((1+K45)) -> 200677.53 | L63: =K63*((1+L45)) -> 218738.51 | M63: =L63*((1+M45)) -> 236237.59 | N63: =M63*((1+N45)) -> 252774.22 | O63: =+I63*O$6 -> 82924.6 | P63: =+I63-O63 -> 82924.6
A64: Cost of Goods Sold (COGS) | D64: ='[1]Acquirer statements'!$C$6 -> 39023 | E64: ='[1]Acquirer statements'!$D$6 -> 48004 | F64: ='[1]Acquirer statements'!$E$6 -> 49123 | G64: ='[1]Acquirer statements'!$F$6 -> 52654 | H64: ='[1]Acquirer statements'!$G$6 -> 56710 | I64: =I63*(I46) -> 69656.664 | J64: =J63*(J46) -> 78446.672 | K64: =K63*(K46) -> 88298.114 | L64: =L63*(L46) -> 98432.329 | M64: =M63*(M46) -> 108669.29 | N64: =N63*(N46) -> 116276.14 | O64: =+I64*O$6 -> 34828.332 | P64: =+I64-O64 -> 34828.332
A65: Gross Profit | D65: =D63-D64 -> 62984 | E65: =E63-E64 -> 70082 | F65: =F63-F64 -> 82222 | G65: =G63-G64 -> 89687 | H65: =H63-H64 -> 94062 | I65: =I63-I64 -> 96192.536 | J65: =J63-J64 -> 103987.45 | K65: =K63-K64 -> 112379.42 | ... P65: =P63-P64 -> 48096.268
A66: Expenses
A67: Marketing, Advertising & Promotion | D67: 26427 | E67: 22658 | F67: 23872 | G67: 23002 | H67: 25245 | I67: =I63*I47 -> 28194.364 | J67: =J63*J47 -> 31013.8 | K67: =K63*K47 -> 34115.18 | L67: =L63*L47 -> 37185.547 | M67: =M63*M47 -> 40160.39 | N67: =N63*N47 -> 42971.618 | O67: =+I67*O$6 -> 14097.182 | P67: =+I67-O67 -> 14097.182
A68: General & Administrative | D68: 10963 | E68: 10125 | F68: 10087 | G68: 11020 | H68: 11412 | I68: =I48 -> 15000 | J68: =J48 -> 15000 | K68: =K48 -> 15000 | L68: =L48 -> 15000 | M68: =M48 -> 15000 | N68: =N48 -> 15000 | O68: =+I68*O$6 -> 7500 | P68: =+I68-O68 -> 7500
A69: Depreciation & Amortization | D69: 19500 | E69: 18150 | F69: 17205 | G69: 16543.5 | H69: 16080.45 | I69: =+I141 -> 7504.21 | J69: =+J141 -> 9003.368 | K69: =+K141 -> 10202.694 | L69: =+L141 -> 11162.156 | M69: =+M141 -> 11929.724 | N69: =+N141 -> 12543.78 | O69: =+I69*O$6 -> 3752.105 | P69: =+I69-O69 -> 3752.105
A70: Interest | D70: 2500 | E70: 2500 | F70: 1500 | G70: 1500 | H70: 1500 | I70: =I148 -> 3000 | J70: =J148 -> 3000 | K70: =K148 -> 1000 | L70: =L148 -> 1000 | M70: =M148 -> 1000 | N70: =N148 -> 1000 | O70: =+I70*O$6 -> 1500 | P70: =+I70-O70 -> 1500
A71: Total Expenses | D71: =SUM(D67:D70) -> 59390 | E71: =SUM(E67:E70) -> 53433 | F71: =SUM(F67:F70) -> 52664 | G71: =SUM(G67:G70) -> 52065.5 | H71: =SUM(H67:H70) -> 54237.45 | I71: =SUM(I67:I70) -> 53698.574 | J71: =SUM(J67:J70) -> 58017.168 | K71: =SUM(K67:K70) -> 60317.875 | ... P71: =SUM(P67:P70) -> 26849.287
A72: Earnings Before Tax | D72: =D65-D71 -> 3594 | E72: =E65-E71 -> 16649 | F72: =F65-F71 -> 29558 | G72: =G65-G71 -> 37621.5 | H72: =H65-H71 -> 39824.55 | I72: =I65-I71 -> 42493.962 | J72: =J65-J71 -> 45970.28 | K72: =K65-K71 -> 52061.543 | ... P72: =P65-P71 -> 21246.981
A74: Taxes | D74: 1120.1708 | E74: 4858.2165 | F74: 8482.8061 | G74: 10908.021 | H74: 11597.665 | I74: =IF(I72>0,I72*I51,0) -> 11898.309 | J74: =IF(J72>0,J72*J51,0) -> 12871.678 | K74: =IF(K72>0,K72*K51,0) -> 14577.232 | L74: =IF(L72>0,L72*L51,0) -> 15668.374 | M74: =IF(M72>0,M72*M51,0) -> 16653.892 | N74: =IF(N72>0,N72*N51,0) -> 18195.151 | O74: =+I74*O$6 -> 5949.1547 | P74: =+I74-O74 -> 5949.1547
A75: Net Earnings | D75: =D72-D74 -> 2473.8292 | E75: =E72-E74 -> 11790.783 | F75: =F72-F74 -> 21075.194 | G75: =G72-G74 -> 26713.479 | H75: =H72-H74 -> 28226.885 | I75: =I72-I74 -> 30595.653 | J75: =J72-J74 -> 33098.602 | K75: =K72-K74 -> 37484.311 | ... P75: =P72-P74 -> 15297.826
A78: Balance Sheet
A80: Assets
A81: Cash | D81: ='[1]Acquirer statements'!$C$23 -> 67971.179 | E81: ='[1]Acquirer statements'!$D$23 -> 81209.913 | F81: ='[1]Acquirer statements'!$E$23 -> 83715.257 | G81: ='[1]Acquirer statements'!$F$23 -> 111069.34 | H81: ='[1]Acquirer statements'!$G$23 -> 139549.52 | I81: =I125 -> 159473.99 | J81: =J125 -> 182573.31 | K81: =K125 -> 190511.04 | L81: =L125 -> 224399.32 | M81: =M125 -> 261247.54 | N81: =N125 -> 303250.39 | O81: =O125 -> 147788.27 | P81: =+I81 -> 159473.99
A82: Accounts Receivable | D82: ='[1]Acquirer statements'!$C$24 -> 5100.35 | E82: ='[1]Acquirer statements'!$D$24 -> 5904.3 | F82: ='[1]Acquirer statements'!$E$24 -> 6567.25 | G82: ='[1]Acquirer statements'!$F$24 -> 7117.05 | H82: ='[1]Acquirer statements'!$G$24 -> 7538.6 | I82: =I63*I52/I5 -> 8178.8647 | J82: =J63*J52/J5 -> 8996.7511 | K82: =K63*K52/K5 -> 9896.4262 | L82: =L63*L52/L5 -> 10757.632 | M82: =M63*M52/M5 -> 11650.073 | N82: =N63*N52/N5 -> 12465.578 | O82: =O63*O52/O5 -> 8246.6453 | P82: =+I82 -> 8178.8647
A83: Inventory | D83: ='[1]Acquirer statements'!$C$25 -> 7804.6 | E83: ='[1]Acquirer statements'!$D$25 -> 9600.8 | F83: ='[1]Acquirer statements'!$E$25 -> 9824.6 | G83: ='[1]Acquirer statements'!$F$25 -> 10530.8 | H83: ='[1]Acquirer statements'!$G$25 -> 11342 | I83: =I64*I53/I5 -> 15267.214 | J83: =J64*J53/J5 -> 19343.015 | K83: =K64*K53/K5 -> 24191.264 | L83: =L64*L53/L5 -> 26894.079 | M83: =M64*M53/M5 -> 29772.409 | N83: =N64*N53/N5 -> 31856.477 | O83: =O64*O53/O5 -> 15393.738 | P83: =+I83 -> 15267.214
A84: Current Assets | D84: =SUM(D81:D83) -> 80876.129 | E84: =SUM(E81:E83) -> 96715.013 | F84: =SUM(F81:F83) -> 100107.11 | G84: =SUM(G81:G83) -> 128717.19 | H84: =SUM(H81:H83) -> 158430.12 | I84: =SUM(I81:I83) -> 182920.07 | J84: =SUM(J81:J83) -> 210913.08 | K84: =SUM(K81:K83) -> 224598.73 | ... P84: =SUM(P81:P83) -> 182920.07
A85: Property & Equipment | D85: =D142 -> 45500 | E85: =E142 -> 42350 | F85: =F142 -> 40145 | G85: =G142 -> 38601.5 | H85: =H142 -> 37521.05 | I85: =I142 -> 45016.84 | J85: =J142 -> 51013.472 | K85: =K142 -> 55810.778 | ... O85: =O142 -> 41268.945 | P85: =+I85 -> 45016.84
A86: Goodwill
A87: Total Assets | D87: =SUM(D84:D86) -> 126376.13 | E87: =SUM(E84:E86) -> 139065.01 | F87: =SUM(F84:F86) -> 140252.11 | G87: =SUM(G84:G86) -> 167318.69 | H87: =SUM(H84:H86) -> 195951.17 | I87: =SUM(I84:I86) -> 227936.91 | J87: =SUM(J84:J86) -> 261926.55 | K87: =SUM(K84:K86) -> 280409.5 | ... P87: =SUM(P84:P86) -> 227936.91
A89: Liabilities
A90: Short Term Debt
A91: Accounts Payable | D91: ='[1]Acquirer statements'!$C$33 -> 3902.3 | E91: ='[1]Acquirer statements'!$D$33 -> 4800.4 | F91: ='[1]Acquirer statements'!$E$33 -> 4912.3 | G91: ='[1]Acquirer statements'!$F$33 -> 5265.4 | H91: ='[1]Acquirer statements'!$G$33 -> 5671 | I91: =I64*I54/I5 -> 7061.0865 | J91: =J64*J54/J5 -> 7952.1284 | K91: =K64*K54/K5 -> 8950.7677 | L91: =L64*L54/L5 -> 9950.8093 | M91: =M64*M54/M5 -> 11015.791 | N91: =N64*N54/N5 -> 11786.897 | O91: =O64*O54/O5 -> 7119.6038 | P91: =+I91 -> 7061.0865
A92: Current Liabilities | D92: =SUM(D90:D91) -> 3902.3 | E92: =SUM(E90:E91) -> 4800.4 | F92: =SUM(F90:F91) -> 4912.3 | G92: =SUM(G90:G91) -> 5265.4 | H92: =SUM(H90:H91) -> 5671 | I92: =SUM(I90:I91) -> 7061.0865 | J92: =SUM(J90:J91) -> 7952.1284 | K92: =SUM(K90:K91) -> 8950.7677 | ... P92: =SUM(P90:P91) -> 7061.0865
A93: Long Term Debt | D93: ='[1]Acquirer statements'!$C$35 -> 50000 | E93: ='[1]Acquirer statements'!$D$35 -> 50000 | F93: ='[1]Acquirer statements'!$E$35 -> 30000 | G93: ='[1]Acquirer statements'!$F$35 -> 30000 | H93: ='[1]Acquirer statements'!$G$35 -> 30000 | I93: =I147 -> 30000 | J93: =J147 -> 30000 | K93: =K147 -> 10000 | L93: =L147 -> 10000 | M93: =M147 -> 10000 | N93: =N147 -> 10000 | O93: =O147 -> 30000 | P93: =+I93 -> 30000
A94: Total Liabilities | D94: =SUM(D92:D93) -> 53902.3 | E94: =SUM(E92:E93) -> 54800.4 | F94: =SUM(F92:F93) -> 34912.3 | G94: =SUM(G92:G93) -> 35265.4 | H94: =SUM(H92:H93) -> 35671 | I94: =SUM(I92:I93) -> 37061.086 | J94: =SUM(J92:J93) -> 37952.128 | K94: =SUM(K92:K93) -> 18950.768 | ... P94: =SUM(P92:P93) -> 37061.086
A95: Shareholder's Equity
A96: Equity Capital | D96: ='[1]Acquirer statements'!$C$38 -> 70000 | E96: ='[1]Acquirer statements'!$D$38 -> 70000 | F96: ='[1]Acquirer statements'!$E$38 -> 70000 | G96: ='[1]Acquirer statements'!$F$38 -> 70000 | H96: ='[1]Acquirer statements'!$G$38 -> 70000 | I96: =H96+I57 -> 70000 | J96: =I96+J57 -> 70000 | K96: =J96+K57 -> 70000 | L96: =K96+L57 -> 70000 | M96: =L96+M57 -> 70000 | N96: =M96+N57 -> 70000 | O96: =H96+O57 -> 70000 | P96: =+I96 -> 70000
A97: Retained Earnings | D97: ='[1]Acquirer statements'!$C$39 -> 2473.8292 | E97: ='[1]Acquirer statements'!$D$39 -> 14264.613 | F97: ='[1]Acquirer statements'!$E$39 -> 35339.807 | G97: ='[1]Acquirer statements'!$F$39 -> 62053.286 | H97: ='[1]Acquirer statements'!$G$39 -> 90280.17 | I97: =+H97+I75-I58 -> 120875.82 | J97: =+I97+J75-J58 -> 153974.42 | K97: =+J97+K75-K58 -> 191458.74 | L97: =+K97+L75-L58 -> 231748.84 | M97: =+L97+M75-M58 -> 274373.13 | N97: =+M97+N75-N58 -> 320960.66 | O97: =+H97+O75-O58 -> 105578 | P97: =+I97 -> 120875.82
A98: Shareholder's Equity | D98: =SUM(D96:D97) -> 72473.829 | E98: =SUM(E96:E97) -> 84264.613 | F98: =SUM(F96:F97) -> 105339.81 | G98: =SUM(G96:G97) -> 132053.29 | H98: =SUM(H96:H97) -> 160280.17 | I98: =SUM(I96:I97) -> 190875.82 | J98: =SUM(J96:J97) -> 223974.42 | K98: =SUM(K96:K97) -> 261458.74 | ... P98: =SUM(P96:P97) -> 190875.82
A99: Total Liabilities & Shareholder's Equity | D99: =D94+D98 -> 126376.13 | E99: =E94+E98 -> 139065.01 | F99: =F94+F98 -> 140252.11 | G99: =G94+G98 -> 167318.69 | H99: =H94+H98 -> 195951.17 | I99: =I98+I94 -> 227936.91 | J99: =J98+J94 -> 261926.55 | K99: =K98+K94 -> 280409.5 | L99: =L98+L94 -> 321699.65 | M99: =M98+M94 -> 365388.92 | N99: =N98+N94 -> 412747.56 | O99: =O98+O94 -> 212697.6 | P99: =P98+P94 -> 227936.91
A101: Check | D101: =D99-D87 -> 0 | E101: =E99-E87 -> 0 | F101: =F99-F87 -> 0 | G101: =G99-G87 -> 0 | H101: =H99-H87 -> 0 | I101: =I99-I87 -> 0 | J101: =J99-J87 -> 0 | K101: =K99-K87 -> 0 | ... P101: =P99-P87 -> 0
A104: Cash Flow Statement
A106: Operating Cash Flow
A107: Net Earnings | D107: =D75 -> 2473.8292 | E107: =E75 -> 11790.783 | F107: =F75 -> 21075.194 | G107: =G75 -> 26713.479 | H107: =H75 -> 28226.885 | I107: =I75 -> 30595.653 | J107: =J75 -> 33098.602 | K107: =K75 -> 37484.311 | ... P107: =P75 -> 15297.826
A108: Plus: Depreciation & Amortization | D108: =D69 -> 19500 | E108: =E69 -> 18150 | F108: =F69 -> 17205 | G108: =G69 -> 16543.5 | H108: =H69 -> 16080.45 | I108: =I69 -> 7504.21 | J108: =J69 -> 9003.368 | K108: =K69 -> 10202.694 | ... P108: =P69 -> 3752.105
A109: Less: Changes in Working Capital | D109: 19500 | E109: =E136 -> 1702.05 | F109: =F136 -> 774.85 | G109: =G136 -> 902.9 | H109: =H136 -> 827.15 | I109: =I136 -> 3175.3922 | J109: =J136 -> 4002.6455 | K109: =K136 -> 4749.285 | L109: =L136 -> 2563.9788 | ... P109: =P136 -> -135.78723
A110: Cash from Operations | D110: =D107+D108-D109 -> 2473.8292 | E110: =E107+E108-E109 -> 28238.733 | F110: =F107+F108-F109 -> 37505.344 | G110: =G107+G108-G109 -> 42354.079 | H110: =H107+H108-H109 -> 43480.185 | I110: =I107+I108-I109 -> 34924.47 | J110: =J107+J108-J109 -> 38099.324 | K110: =K107+K108-K109 -> 42937.72 | ... P110: =P107+P108-P109 -> 19185.719
A112: Investing Cash Flow
A113: Investments in Property & Equipment | D113: =-D140 -> -15000 | E113: =-E140 -> -15000 | F113: =-F140 -> -15000 | G113: =-G140 -> -15000 | H113: =-H140 -> -15000 | I113: =-I140 -> -15000 | J113: =-J140 -> -15000 | K113: =-K140 -> -15000 | ... P113: =-P140 -> -7500
A114: Investments in Businesses
A115: Cash from Investing | D115: =SUM(D113:D114) -> -15000 | E115: =SUM(E113:E114) -> -15000 | F115: =SUM(F113:F114) -> -15000 | G115: =SUM(G113:G114) -> -15000 | H115: =SUM(H113:H114) -> -15000 | I115: =SUM(I113:I114) -> -15000 | J115: =SUM(J113:J114) -> -15000 | K115: =SUM(K113:K114) -> -15000 | ... P115: =SUM(P113:P114) -> -7500
A117: Financing Cash Flow
A118: Issuance (repayment) of debt | D118: 0 | E118: 0 | G118: 0 | H118: 0 | I118: =I146 -> 0 | J118: =J146 -> 0 | K118: =K146 -> -20000 | L118: =L146 -> 0 | M118: =M146 -> 0 | N118: =N146 -> 0 | O118: =O146 -> 0 | P118: =P146 -> 0
A119: Issuance (repayment) of equity | E119: 0 | F119: -20000 | G119: 0 | H119: 0 | I119: =I57 -> 0 | J119: =J57 -> 0 | K119: =K57 -> 0 | L119: =L57 -> 0 | M119: =M57 -> 0 | N119: =N57 -> 0 | O119: =O57 -> 0 | P119: =P57 -> 0
A120: Payment of Dividends | D120: 0 | E120: 0 | F120: 0 | G120: 0 | H120: 0 | I120: =-I58 -> 0 | J120: =-J58 -> 0 | K120: =-K58 -> 0 | L120: =-L58 -> 0 | M120: =-M58 -> -200 | N120: =-N58 -> -200 | O120: =-O58 -> 0 | P120: =-P58 -> 0
...

Sheet Target Model
D1: Historical Results | I1: Forecast Period | O1: Stub
A2: ='M&A Assumptions & Analysis'!D7&" Model" -> Brick 'n' Mortar Co Model | D2: 2020 | E2: =+D2+1 -> 2021 | F2: =+E2+1 -> 2022 | G2: =+F2+1 -> 2023 | H2: =+G2+1 -> 2024 | I2: =+H2+1 -> 2025 | J2: =+I2+1 -> 2026 | K2: =+J2+1 -> 2027 | L2: =+K2+1 -> 2028 | ... N2: =+M2+1 -> 2030 | O2: =+O4 -> 45838 | P2: =+P4 -> 46022
A3: Balance Sheet Check | D3: =IFERROR(IF(ABS(D101)>1,"ERROR","ok"),"ok") -> ok | E3: =IFERROR(IF(ABS(E101)>1,"ERROR","ok"),"ok") -> ok | F3: =IFERROR(IF(ABS(F101)>1,"ERROR","ok"),"ok") -> ok | G3: =IFERROR(IF(ABS(G101)>1,"ERROR","ok"),"ok") -> ok | H3: =IFERROR(IF(ABS(H101)>1,"ERROR","ok"),"ok") -> ok | I3: =IFERROR(IF(ABS(I101)>1,"ERROR","ok"),"ok") -> ok | J3: =IFERROR(IF(ABS(J101)>1,"ERROR","ok"),"ok") -> ok | K3: =IFERROR(IF(ABS(K101)>1,"ERROR","ok"),"ok") -> ok | ... N3: =IFERROR(IF(ABS(N101)>1,"ERROR","ok"),"ok") -> ok
A4: End of Period | D4: 41274 | E4: =EOMONTH(D4,12) -> 41639 | F4: =EOMONTH(E4,12) -> 42004 | G4: =EOMONTH(F4,12) -> 42369 | H4: =EOMONTH(G4,12) -> 42735 | I4: =EOMONTH(H4,12) -> 43100 | J4: =EOMONTH(I4,12) -> 43465 | K4: =EOMONTH(J4,12) -> 43830 | L4: =EOMONTH(K4,12) -> 44196 | ... N4: =EOMONTH(M4,12) -> 44926 | O4: =+'M&A Assumptions & Analysis'!D10 -> 45838 | P4: =+EOMONTH(O4,P6*12) -> 46022
A5: Days in Period | D5: 366 | E5: =E4-D4 -> 365 | F5: =F4-E4 -> 365 | G5: =G4-F4 -> 365 | H5: =H4-G4 -> 366 | I5: =I4-H4 -> 365 | J5: =J4-I4 -> 365 | K5: =K4-J4 -> 365 | L5: =L4-K4 -> 366 | ... N5: =N4-M4 -> 365 | O5: =+O4-H4 -> 3103 | P5: =+P4-O4 -> 184
A6: Fraction of Year | D6: 1 | E6: =D6 -> 1 | F6: =E6 -> 1 | G6: =F6 -> 1 | H6: =G6 -> 1 | I6: =H6 -> 1 | J6: =I6 -> 1 | K6: =J6 -> 1 | L6: =K6 -> 1 | ... N6: =M6 -> 1 | O6: 0.5 | P6: =1-O6 -> 0.5
A8: Assumptions
H10: LIVE SCENARIO | I10: 1
A12: SCENARIO 1
A13: Revenue Growth (% Change) | I13: 0.15 | J13: 0.15 | K13: 0.12 | L13: 0.1 | M13: 0.08 | N13: 0.06 | O13: 0.15 | P13: 0.15
A14: Cost of Goods Sold (% of Revenue) | I14: 0.42 | J14: 0.41 | K14: 0.4 | L14: 0.4 | M14: 0.4 | N14: 0.4 | O14: 0.42 | P14: 0.42
A15: Salaries and Benefits (% of Revenue) | I15: 0.16 | J15: 0.16 | K15: 0.16 | L15: 0.16 | M15: 0.16 | N15: 0.16 | O15: 0.16 | P15: 0.16
A16: Rent and Overhead ($000's) | I16: 7000 | J16: 7000 | K16: 7000 | L16: 7000 | M16: 7000 | N16: 7000 | O16: 7000 | P16: 7000
A17: Depreciation & Amortization (% of PP&E) | I17: 0.2 | J17: 0.2 | K17: 0.2 | L17: 0.2 | M17: 0.2 | N17: 0.2 | O17: 0.2 | P17: 0.2
A18: Interest (% of Debt) | I18: 0.08 | J18: 0.08 | K18: 0.08 | L18: 0.08 | M18: 0.08 | N18: 0.08 | O18: 0.08 | P18: 0.08
A19: Tax Rate (% of Earnings Before Tax) | I19: 0.32 | J19: 0.32 | K19: 0.32 | L19: 0.32 | M19: 0.32 | N19: 0.32 | O19: 0.32 | P19: 0.32
A20: Accounts Receivable (Days) | I20: 22 | J20: 18 | K20: 18 | L20: 18 | M20: 18 | N20: 18 | O20: 22 | P20: 22
A21: Inventory (Days) | I21: 75 | J21: 75 | K21: 75 | L21: 75 | M21: 75 | N21: 75 | O21: 75 | P21: 75
A22: Accounts Payable (Days) | I22: 39 | J22: 39 | K22: 39 | L22: 39 | M22: 39 | N22: 39 | O22: 39 | P22: 39
A23: Capital Expenditures ($000's) | I23: 5750 | J23: 5750 | K23: 5750 | L23: 5750 | M23: 5750 | N23: 5750 | O23: 5750 | P23: 5750
A24: Debt Issuance (Repayment) ($000's) | I24: 0 | J24: 0 | K24: 0 | L24: 0 | M24: 0 | N24: -10000 | O24: 0 | P24: 0
... A26: Payment of Dividends | I26: 0 | J26: 0 | K26: 0 | L26: 0 | M26: 200 | N26: 200 | O26: 0 | P26: 0
A28: SCENARIO 2
A29: Revenue Growth (% Change) | I29: 0.05 | J29: 0.045 | K29: 0.04 | L29: 0.035 | M29: 0.03 | N29: 0.03 | O29: 0.05 | P29: 0.05
A30: Cost of Goods Sold (% of Revenue) | I30: 0.37 | J30: 0.37 | K30: 0.36 | L30: 0.36 | M30: 0.35 | N30: 0.35 | O30: 0.37 | P30: 0.37
A31: Salaries and Benefits (% of Revenue) | I31: 0.17 | J31: 0.17 | K31: 0.17 | L31: 0.17 | M31: 0.17 | N31: 0.17 | O31: 0.17 | P31: 0.17
A32: Rent and Overhead ($000's) | I32: 10000 | J32: 10000 | K32: 10000 | L32: 10000 | M32: 10000 | N32: 10000 | O32: 10000 | P32: 10000
A33: Depreciation & Amortization (% of PP&E) | I33: 0.2 | J33: 0.2 | K33: 0.2 | L33: 0.2 | M33: 0.2 | N33: 0.2 | O33: 0.2 | P33: 0.2
A34: Interest (% of Debt) | I34: 0.05 | J34: 0.05 | K34: 0.05 | L34: 0.05 | M34: 0.05 | N34: 0.05 | O34: 0.05 | P34: 0.05
A35: Tax Rate (% of Earnings Before Tax) | I35: 0.28 | J35: 0.28 | K35: 0.28 | L35: 0.28 | M35: 0.28 | N35: 0.28 | O35: 0.28 | P35: 0.28
A36: Accounts Receivable (Days) | I36: 18 | J36: 18 | K36: 18 | L36: 18 | M36: 18 | N36: 18 | O36: 18 | P36: 18
A37: Inventory (Days) | I37: 73 | J37: 73 | K37: 73 | L37: 73 | M37: 73 | N37: 73 | O37: 73 | P37: 73
A38: Accounts Payable (Days) | I38: 37 | J38: 37 | K38: 37 | L38: 37 | M38: 37 | N38: 37 | O38: 37 | P38: 37
A39: Capital Expenditures ($000's) | I39: 15000 | J39: 15000 | K39: 15000 | L39: 15000 | M39: 15000 | N39: 15000 | O39: 15000 | P39: 15000
A40: Debt Issuance (Repayment) ($000's) | I40: 0 | J40: 0 | K40: -20000 | L40: 0 | M40: 0 | N40: 0 | O40: 0 | P40: 0
... A42: Payment of Dividends | I42: 0 | J42: 0 | K42: 0 | L42: 0 | M42: 100 | N42: 100 | O42: 0 | P42: 0
A44: LIVE SCENARIO
A45: Revenue Growth (% Change) | I45: =CHOOSE($I$10,I13,I29) -> 0.15 | J45: =CHOOSE($I$10,J13,J29) -> 0.15 | K45: =CHOOSE($I$10,K13,K29) -> 0.12 | L45: =CHOOSE($I$10,L13,L29) -> 0.1 | M45: =CHOOSE($I$10,M13,M29) -> 0.08 | N45: =CHOOSE($I$10,N13,N29) -> 0.06 | O45: =CHOOSE($I$10,O13,O29) -> 0.15 | P45: =CHOOSE($I$10,P13,P29) -> 0.15
A46: Cost of Goods Sold (% of Revenue) | I46: =CHOOSE($I$10,I14,I30) -> 0.42 | J46: =CHOOSE($I$10,J14,J30) -> 0.41 | K46: =CHOOSE($I$10,K14,K30) -> 0.4 | L46: =CHOOSE($I$10,L14,L30) -> 0.4 | M46: =CHOOSE($I$10,M14,M30) -> 0.4 | N46: =CHOOSE($I$10,N14,N30) -> 0.4 | O46: =CHOOSE($I$10,O14,O30) -> 0.42 | P46: =CHOOSE($I$10,P14,P30) -> 0.42
A47: Marketing, Advertising & Promotion (% of Revenue) | I47: =CHOOSE($I$10,I15,I31) -> 0.16 | J47: =CHOOSE($I$10,J15,J31) -> 0.16 | K47: =CHOOSE($I$10,K15,K31) -> 0.16 | L47: =CHOOSE($I$10,L15,L31) -> 0.16 | M47: =CHOOSE($I$10,M15,M31) -> 0.16 | N47: =CHOOSE($I$10,N15,N31) -> 0.16 | O47: =CHOOSE($I$10,O15,O31) -> 0.16 | P47: =CHOOSE($I$10,P15,P31) -> 0.16
A48: General & Administrative ($000's) | I48: =CHOOSE($I$10,I16,I32) -> 7000 | J48: =CHOOSE($I$10,J16,J32) -> 7000 | K48: =CHOOSE($I$10,K16,K32) -> 7000 | L48: =CHOOSE($I$10,L16,L32) -> 7000 | M48: =CHOOSE($I$10,M16,M32) -> 7000 | N48: =CHOOSE($I$10,N16,N32) -> 7000 | O48: =CHOOSE($I$10,O16,O32) -> 7000 | P48: =CHOOSE($I$10,P16,P32) -> 7000
A49: Depreciation & Amortization (% of PP&E) | I49: =CHOOSE($I$10,I17,I33) -> 0.2 | J49: =CHOOSE($I$10,J17,J33) -> 0.2 | K49: =CHOOSE($I$10,K17,K33) -> 0.2 | L49: =CHOOSE($I$10,L17,L33) -> 0.2 | M49: =CHOOSE($I$10,M17,M33) -> 0.2 | N49: =CHOOSE($I$10,N17,N33) -> 0.2 | O49: =CHOOSE($I$10,O17,O33) -> 0.2 | P49: =CHOOSE($I$10,P17,P33) -> 0.2
A50: Interest (% of Debt) | D50: 0.08 | E50: 0.08 | F50: 0.08 | G50: 0.08 | H50: 0.08 | I50: =CHOOSE($I$10,I18,I34) -> 0.08 | J50: =CHOOSE($I$10,J18,J34) -> 0.08 | K50: =CHOOSE($I$10,K18,K34) -> 0.08 | L50: =CHOOSE($I$10,L18,L34) -> 0.08 | M50: =CHOOSE($I$10,M18,M34) -> 0.08 | N50: =CHOOSE($I$10,N18,N34) -> 0.08 | O50: =CHOOSE($I$10,O18,O34) -> 0.08 | P50: =CHOOSE($I$10,P18,P34) -> 0.08
A51: Tax Rate (% of Earnings Before Tax) | I51: =CHOOSE($I$10,I19,I35) -> 0.32 | J51: =CHOOSE($I$10,J19,J35) -> 0.32 | K51: =CHOOSE($I$10,K19,K35) -> 0.32 | L51: =CHOOSE($I$10,L19,L35) -> 0.32 | M51: =CHOOSE($I$10,M19,M35) -> 0.32 | N51: =CHOOSE($I$10,N19,N35) -> 0.32 | O51: =CHOOSE($I$10,O19,O35) -> 0.32 | P51: =CHOOSE($I$10,P19,P35) -> 0.32
A52: Accounts Receivable (Days) | I52: =CHOOSE($I$10,I20,I36) -> 22 | J52: =CHOOSE($I$10,J20,J36) -> 18 | K52: =CHOOSE($I$10,K20,K36) -> 18 | L52: =CHOOSE($I$10,L20,L36) -> 18 | M52: =CHOOSE($I$10,M20,M36) -> 18 | N52: =CHOOSE($I$10,N20,N36) -> 18 | O52: =CHOOSE($I$10,O20,O36) -> 22 | P52: =CHOOSE($I$10,P20,P36) -> 22
A53: Inventory (Days) | I53: =CHOOSE($I$10,I21,I37) -> 75 | J53: =CHOOSE($I$10,J21,J37) -> 75 | K53: =CHOOSE($I$10,K21,K37) -> 75 | L53: =CHOOSE($I$10,L21,L37) -> 75 | M53: =CHOOSE($I$10,M21,M37) -> 75 | N53: =CHOOSE($I$10,N21,N37) -> 75 | O53: =CHOOSE($I$10,O21,O37) -> 75 | P53: =CHOOSE($I$10,P21,P37) -> 75
A54: Accounts Payable (Days) | I54: =CHOOSE($I$10,I22,I38) -> 39 | J54: =CHOOSE($I$10,J22,J38) -> 39 | K54: =CHOOSE($I$10,K22,K38) -> 39 | L54: =CHOOSE($I$10,L22,L38) -> 39 | M54: =CHOOSE($I$10,M22,M38) -> 39 | N54: =CHOOSE($I$10,N22,N38) -> 39 | O54: =CHOOSE($I$10,O22,O38) -> 39 | P54: =CHOOSE($I$10,P22,P38) -> 39
A55: Capital Expenditures ($000's) | I55: =CHOOSE($I$10,I23,I39) -> 5750 | J55: =CHOOSE($I$10,J23,J39) -> 5750 | K55: =CHOOSE($I$10,K23,K39) -> 5750 | L55: =CHOOSE($I$10,L23,L39) -> 5750 | M55: =CHOOSE($I$10,M23,M39) -> 5750 | N55: =CHOOSE($I$10,N23,N39) -> 5750 | O55: =CHOOSE($I$10,O23,O39) -> 5750 | P55: =CHOOSE($I$10,P23,P39) -> 5750
A56: Debt Issuance (Repayment) ($000's) | I56: =CHOOSE($I$10,I24,I40) -> 0 | J56: =CHOOSE($I$10,J24,J40) -> 0 | K56: =CHOOSE($I$10,K24,K40) -> 0 | L56: =CHOOSE($I$10,L24,L40) -> 0 | M56: =CHOOSE($I$10,M24,M40) -> 0 | N56: =CHOOSE($I$10,N24,N40) -> -10000 | O56: =CHOOSE($I$10,O24,O40) -> 0 | P56: =CHOOSE($I$10,P24,P40) -> 0
A57: Equity Issued (Repaid) ($000's) | I57: =CHOOSE($I$10,I25,I41) -> 0 | J57: =CHOOSE($I$10,J25,J41) -> 0 | K57: =CHOOSE($I$10,K25,K41) -> 0 | L57: =CHOOSE($I$10,L25,L41) -> 0 | M57: =CHOOSE($I$10,M25,M41) -> 0 | N57: =CHOOSE($I$10,N25,N41) -> 0 | O57: =CHOOSE($I$10,O25,O41) -> 0 | P57: =CHOOSE($I$10,P25,P41) -> 0
A58: Payment of Dividends | I58: =CHOOSE($I$10,I26,I42) -> 0 | J58: =CHOOSE($I$10,J26,J42) -> 0 | K58: =CHOOSE($I$10,K26,K42) -> 0 | L58: =CHOOSE($I$10,L26,L42) -> 0 | M58: =CHOOSE($I$10,M26,M42) -> 200 | N58: =CHOOSE($I$10,N26,N42) -> 200 | O58: =CHOOSE($I$10,O26,O42) -> 0 | P58: =CHOOSE($I$10,P26,P42) -> 0
A61: Income Statement
A63: Revenue | D63: ='[1]Target statements'!$C$5 -> 57127.576 | E63: ='[1]Target statements'!$D$5 -> 66132.392 | F63: ='[1]Target statements'!$E$5 -> 73557.908 | G63: ='[1]Target statements'!$F$5 -> 79716.062 | H63: ='[1]Target statements'!$G$5 -> 84437.724 | I63: =H63*((1+I45)) -> 97103.383 | J63: =I63*((1+J45)) -> 111668.89 | K63: =J63*((1+K45)) -> 125069.16 | L63: =K63*((1+L45)) -> 137576.07 | M63: =L63*((1+M45)) -> 148582.16 | N63: =M63*((1+N45)) -> 157497.09 | O63: =+I63*O$6 -> 48551.691 | P63: =+I63-O63 -> 48551.691
A64: Cost of Goods Sold (COGS) | D64: ='[1]Target statements'!$C$6 -> 21854.279 | E64: ='[1]Target statements'!$D$6 -> 26883.961 | F64: ='[1]Target statements'!$E$6 -> 27510.641 | G64: ='[1]Target statements'!$F$6 -> 29488.127 | H64: ='[1]Target statements'!$G$6 -> 31759.633 | I64: =I63*(I46) -> 40783.421 | J64: =J63*(J46) -> 45784.245 | K64: =K63*(K46) -> 50027.663 | L64: =L63*(L46) -> 55030.429 | M64: =M63*(M46) -> 59432.863 | N64: =N63*(N46) -> 62998.835 | O64: =+I64*O$6 -> 20391.71 | P64: =+I64-O64 -> 20391.71
A65: Gross Profit | D65: =D63-D64 -> 35273.297 | E65: =E63-E64 -> 39248.432 | F65: =F63-F64 -> 46047.267 | G65: =G63-G64 -> 50227.935 | H65: =H63-H64 -> 52678.091 | I65: =I63-I64 -> 56319.962 | J65: =J63-J64 -> 65884.645 | K65: =K63-K64 -> 75041.494 | ... P65: =P63-P64 -> 28159.981
A66: Expenses
A67: Marketing, Advertising & Promotion | D67: ='[1]Target statements'!$C$9 -> 14800.067 | E67: ='[1]Target statements'!$D$9 -> 12689.292 | F67: ='[1]Target statements'!$E$9 -> 13369.176 | G67: ='[1]Target statements'!$F$9 -> 12881.944 | H67: ='[1]Target statements'!$G$9 -> 14138.105 | I67: =I63*I47 -> 15536.541 | J67: =J63*J47 -> 17867.022 | K67: =K63*K47 -> 20011.065 | L67: =L63*L47 -> 22012.172 | M67: =M63*M47 -> 23773.145 | N67: =N63*N47 -> 25199.534 | O67: =+I67*O$6 -> 7768.2706 | P67: =+I67-O67 -> 7768.2706
A68: General & Administrative | D68: ='[1]Target statements'!$C$10 -> 6139.6729 | E68: ='[1]Target statements'!$D$10 -> 5670.3629 | F68: ='[1]Target statements'!$E$10 -> 5649.0815 | G68: ='[1]Target statements'!$F$10 -> 6171.595 | H68: ='[1]Target statements'!$G$10 -> 6391.129 | I68: =I48 -> 7000 | J68: =J48 -> 7000 | K68: =K48 -> 7000 | L68: =L48 -> 7000 | M68: =M48 -> 7000 | N68: =N48 -> 7000 | O68: =+I68*O$6 -> 3500 | P68: =+I68-O68 -> 3500
A69: Depreciation & Amortization | D69: ='[1]Target statements'!$C$11 -> 10920.699 | E69: ='[1]Target statements'!$D$11 -> 10164.651 | F69: ='[1]Target statements'!$E$11 -> 9635.4167 | G69: ='[1]Target statements'!$F$11 -> 9264.953 | H69: ='[1]Target statements'!$G$11 -> 9005.6284 | I69: =+I141 -> 4202.6266 | J69: =+J141 -> 4512.1013 | K69: =+K141 -> 4759.681 | L69: =+L141 -> 4957.7448 | M69: =+M141 -> 5116.1958 | N69: =+N141 -> 5242.9567 | O69: =+I69*O$6 -> 2101.3133 | P69: =+I69-O69 -> 2101.3133
A70: Interest | D70: ='[1]Target statements'!$C$12 -> 1400.0896 | E70: ='[1]Target statements'!$D$12 -> 1400.0896 | F70: ='[1]Target statements'!$E$12 -> 840.05376 | G70: ='[1]Target statements'!$F$12 -> 840.05376 | H70: ='[1]Target statements'!$G$12 -> 840.05376 | I70: =I148 -> 1344.086 | J70: =J148 -> 1344.086 | K70: =K148 -> 1344.086 | L70: =L148 -> 1344.086 | M70: =M148 -> 1344.086 | N70: =N148 -> 544.08602 | O70: =+I70*O$6 -> 672.04301 | P70: =+I70-O70 -> 672.04301
A71: Total Expenses | D71: =SUM(D67:D70) -> 33260.529 | E71: =SUM(E67:E70) -> 29924.395 | F71: =SUM(F67:F70) -> 29493.728 | G71: =SUM(G67:G70) -> 29158.546 | H71: =SUM(H67:H70) -> 30374.916 | I71: =SUM(I67:I70) -> 28083.254 | J71: =SUM(J67:J70) -> 30723.21 | K71: =SUM(K67:K70) -> 33114.832 | ... P71: =SUM(P67:P70) -> 14041.627
A72: Earnings Before Tax | D72: =D65-D71 -> 2012.7688 | E72: =E65-E71 -> 9324.0367 | F72: =F65-F71 -> 16553.539 | G72: =G65-G71 -> 21069.388 | H72: =H65-H71 -> 22303.175 | I72: =I65-I71 -> 28236.708 | J72: =J65-J71 -> 35161.435 | K72: =K65-K71 -> 41926.662 | ... P72: =P65-P71 -> 14118.354
A74: Taxes | D74: ='[1]Acquirer statements'!$C$16 -> 1120.1708 | E74: ='[1]Acquirer statements'!$D$16 -> 4858.2165 | F74: ='[1]Acquirer statements'!$E$16 -> 8482.8061 | G74: ='[1]Acquirer statements'!$F$16 -> 10908.021 | H74: ='[1]Acquirer statements'!$G$16 -> 11597.665 | I74: =IF(I72>0,I72*I51,0) -> 9035.7466 | J74: =IF(J72>0,J72*J51,0) -> 11251.659 | K74: =IF(K72>0,K72*K51,0) -> 13416.532 | L74: =IF(L72>0,L72*L51,0) -> 15114.125 | M74: =IF(M72>0,M72*M51,0) -> 16613.078 | N74: =IF(N72>0,N72*N51,0) -> 18083.736 | O74: =+I74*O$6 -> 4517.8733 | P74: =+I74-O74 -> 4517.8733
A75: Net Earnings | D75: =D72-D74 -> 892.59802 | E75: =E72-E74 -> 4465.8202 | F75: =F72-F74 -> 8070.7333 | G75: =G72-G74 -> 10161.367 | H75: =H72-H74 -> 10705.51 | I75: =I72-I74 -> 19200.962 | J75: =J72-J74 -> 23909.776 | K75: =K72-K74 -> 28510.13 | ... P75: =P72-P74 -> 9600.4808
A78: Balance Sheet
A80: Assets
A81: Cash | D81: ='[1]Target statements'!$C$23 -> 37573.462 | E81: ='[1]Target statements'!$D$23 -> 42850.186 | F81: ='[1]Target statements'!$E$23 -> 40521.137 | G81: ='[1]Target statements'!$F$23 -> 51041.264 | H81: ='[1]Target statements'!$G$23 -> 61888.631 | I81: =I125 -> 77064.655 | J81: =J125 -> 99589.148 | K81: =K125 -> 126029.6 | L81: =L125 -> 156278.02 | M81: =M125 -> 189736.66 | N81: =N125 -> 216666.2 | O81: =O125 -> 77532.337 | P81: =+I81 -> 77064.655
A82: Accounts Receivable | D82: ='[1]Target statements'!$C$24 -> 2856.3788 | E82: ='[1]Target statements'!$D$24 -> 3306.6196 | F82: ='[1]Target statements'!$E$24 -> 3677.8954 | G82: ='[1]Target statements'!$F$24 -> 3985.8031 | H82: ='[1]Target statements'!$G$24 -> 4221.8862 | I82: =I63*I52/I5 -> 5852.8066 | J82: =J63*J52/J5 -> 5506.959 | K82: =K63*K52/K5 -> 6167.794 | L82: =L63*L52/L5 -> 6766.0364 | M82: =M63*M52/M5 -> 7327.3393 | N82: =N63*N52/N5 -> 7766.9797 | O82: =O63*O52/O5 -> 344.22727 | P82: =+I82 -> 5852.8066
A83: Inventory | D83: ='[1]Target statements'!$C$25 -> 4370.8557 | E83: ='[1]Target statements'!$D$25 -> 5376.7921 | F83: ='[1]Target statements'!$E$25 -> 5502.1281 | G83: ='[1]Target statements'!$F$25 -> 5897.6254 | H83: ='[1]Target statements'!$G$25 -> 6351.9265 | I83: =I64*I53/I5 -> 8380.1549 | J83: =J64*J53/J5 -> 9407.7216 | K83: =K64*K53/K5 -> 10279.657 | L83: =L64*L53/L5 -> 11276.727 | M83: =M64*M53/M5 -> 12212.232 | N83: =N64*N53/N5 -> 12944.966 | O83: =O64*O53/O5 -> 492.87086 | P83: =+I83 -> 8380.1549
A84: Current Assets | D84: =SUM(D81:D83) -> 44800.696 | E84: =SUM(E81:E83) -> 51533.597 | F84: =SUM(F81:F83) -> 49701.161 | G84: =SUM(G81:G83) -> 60924.692 | H84: =SUM(H81:H83) -> 72462.444 | I84: =SUM(I81:I83) -> 91297.617 | J84: =SUM(J81:J83) -> 114503.83 | K84: =SUM(K81:K83) -> 142477.05 | ... P84: =SUM(P81:P83) -> 91297.617
A85: Property & Equipment | D85: ='[1]Target statements'!$C$27 -> 25481.631 | E85: ='[1]Target statements'!$D$27 -> 23717.518 | F85: ='[1]Target statements'!$E$27 -> 22482.639 | G85: ='[1]Target statements'!$F$27 -> 21618.224 | H85: ='[1]Target statements'!$G$27 -> 21013.133 | I85: =I142 -> 22560.506 | J85: =J142 -> 23798.405 | K85: =K142 -> 24788.724 | L85: =L142 -> 25580.979 | M85: =M142 -> 26214.783 | N85: =N142 -> 26721.827 | O85: =O142 -> 21786.82 | P85: =+I85 -> 22560.506
A86: Goodwill
A87: Total Assets | D87: =SUM(D84:D86) -> 70282.327 | E87: =SUM(E84:E86) -> 75251.115 | F87: =SUM(F84:F86) -> 72183.8 | G87: =SUM(G84:G86) -> 82542.916 | H87: =SUM(H84:H86) -> 93475.577 | I87: =SUM(I84:I86) -> 113858.12 | J87: =SUM(J84:J86) -> 138302.23 | K87: =SUM(K84:K86) -> 167265.77 | ... P87: =SUM(P84:P86) -> 113858.12
A89: Liabilities
A90: Short Term Debt | D90: 0 | E90: 0 | F90: 0 | G90: 0 | H90: 0
A91: Accounts Payable | D91: ='[1]Target statements'!$C$33 -> 2185.4279 | E91: ='[1]Target statements'!$D$33 -> 2688.3961 | F91: ='[1]Target statements'!$E$33 -> 2751.0641 | G91: ='[1]Target statements'!$F$33 -> 2948.8127 | H91: ='[1]Target statements'!$G$33 -> 3175.9633 | I91: =I64*I54/I5 -> 4357.6806 | J91: =J64*J54/J5 -> 4892.0152 | K91: =K64*K54/K5 -> 5345.4215 | L91: =L64*L54/L5 -> 5863.8982 | M91: =M64*M54/M5 -> 6350.3607 | N91: =N64*N54/N5 -> 6731.3824 | O91: =O64*O54/O5 -> 256.29285 | P91: =+I91 -> 4357.6806
A92: Current Liabilities | D92: =SUM(D90:D91) -> 2185.4279 | E92: =SUM(E90:E91) -> 2688.3961 | F92: =SUM(F90:F91) -> 2751.0641 | G92: =SUM(G90:G91) -> 2948.8127 | H92: =SUM(H90:H91) -> 3175.9633 | I92: =SUM(I90:I91) -> 4357.6806 | J92: =SUM(J90:J91) -> 4892.0152 | K92: =SUM(K90:K91) -> 5345.4215 | ... P92: =SUM(P90:P91) -> 4357.6806
A93: Long Term Debt | D93: ='[2]Target statements'!$C$35 -> 28001.792 | E93: ='[1]Target statements'!$D$35 -> 28001.792 | F93: ='[1]Target statements'!$E$35 -> 16801.075 | G93: ='[1]Target statements'!$F$35 -> 16801.075 | H93: ='[1]Target statements'!$G$35 -> 16801.075 | I93: =I147 -> 16801.075 | J93: =J147 -> 16801.075 | K93: =K147 -> 16801.075 | L93: =L147 -> 16801.075 | M93: =M147 -> 16801.075 | N93: =N147 -> 6801.0753 | O93: =O147 -> 16801.075 | P93: =+I93 -> 16801.075
A94: Total Liabilities | D94: =SUM(D92:D93) -> 30187.22 | E94: =SUM(E92:E93) -> 30690.188 | F94: =SUM(F92:F93) -> 19552.139 | G94: =SUM(G92:G93) -> 19749.888 | H94: =SUM(H92:H93) -> 19977.039 | I94: =SUM(I92:I93) -> 21158.756 | J94: =SUM(J92:J93) -> 21693.09 | K94: =SUM(K92:K93) -> 22146.497 | ... P94: =SUM(P92:P93) -> 21158.756
A95: Shareholder's Equity
A96: Equity Capital | D96: ='[1]Target statements'!$C$38 -> 39202.509 | E96: ='[1]Target statements'!$D$38 -> 39202.509 | F96: ='[1]Target statements'!$D$38 -> 39202.509 | G96: ='[1]Target statements'!$D$38 -> 39202.509 | H96: ='[1]Target statements'!$D$38 -> 39202.509 | I96: =H96+I57 -> 39202.509 | J96: =I96+J57 -> 39202.509 | K96: =J96+K57 -> 39202.509 | L96: =K96+L57 -> 39202.509 | M96: =L96+M57 -> 39202.509 | N96: =M96+N57 -> 39202.509 | O96: =H96+O57 -> 39202.509 | P96: =+I96 -> 39202.509
A97: Retained Earnings | D97: ='[2]Target statements'!$C$39 -> 893 | E97: =+D97+E107 -> 5358.8202 | F97: =+E97+F107 -> 13429.554 | G97: =+F97+G107 -> 23590.921 | H97: =+G97+H107 -> 34296.431 | I97: =+H97+I75-I58 -> 53497.393 | J97: =+I97+J75-J58 -> 77407.169 | K97: =+J97+K75-K58 -> 105917.3 | L97: =+K97+L75-L58 -> 138034.81 | M97: =+L97+M75-M58 -> 173137.6 | N97: =+M97+N75-N58 -> 211365.54 | O97: =+H97+O75-O58 -> 43896.912 | P97: =+I97 -> 53497.393
A98: Shareholder's Equity | D98: =SUM(D96:D97) -> 40095.509 | E98: =SUM(E96:E97) -> 44561.329 | F98: =SUM(F96:F97) -> 52632.063 | G98: =SUM(G96:G97) -> 62793.43 | H98: =SUM(H96:H97) -> 73498.94 | I98: =SUM(I96:I97) -> 92699.902 | J98: =SUM(J96:J97) -> 116609.68 | K98: =SUM(K96:K97) -> 145119.81 | ... P98: =SUM(P96:P97) -> 92699.902
A99: Total Liabilities & Shareholder's Equity | D99: =D94+D98 -> 70282.729 | E99: =E94+E98 -> 75251.517 | F99: =F94+F98 -> 72184.202 | G99: =G94+G98 -> 82543.318 | H99: =H94+H98 -> 93475.979 | I99: =I98+I94 -> 113858.66 | J99: =J98+J94 -> 138302.77 | K99: =K98+K94 -> 167266.3 | L99: =L98+L94 -> 199902.3 | M99: =M98+M94 -> 235491.55 | N99: =N98+N94 -> 264100.51 | O99: =O98+O94 -> 100156.79 | P99: =P98+P94 -> 113858.66
A101: Check | D101: =D99-D87 -> 0.4019828 | E101: =E99-E87 -> 0.4019828 | F101: =F99-F87 -> 0.4019828 | G101: =G99-G87 -> 0.4019828 | H101: =H99-H87 -> 0.4019828 | I101: =I99-I87 -> 0.53459928 | J101: =J99-J87 -> 0.53459928 | K101: =K99-K87 -> 0.53459928 | ... P101: =P99-P87 -> 0.53459928
A104: Cash Flow Statement
A106: Operating Cash Flow
A107: Net Earnings | D107: =D75 -> 892.59802 | E107: =E75 -> 4465.8202 | F107: =F75 -> 8070.7333 | G107: =G75 -> 10161.367 | H107: =H75 -> 10705.51 | I107: =I75 -> 19200.962 | J107: =J75 -> 23909.776 | K107: =K75 -> 28510.13 | ... P107: =P75 -> 9600.4808
A108: Plus: Depreciation & Amortization | D108: =D69 -> 10920.699 | E108: =E69 -> 10164.651 | F108: =F69 -> 9635.4167 | G108: =G69 -> 9264.953 | H108: =H69 -> 9005.6284 | I108: =I69 -> 4202.6266 | J108: =J69 -> 4512.1013 | K108: =K69 -> 4759.681 | ... P108: =P69 -> 2101.3133
A109: Less: Changes in Working Capital | E109: =E136 -> 953.20901 | F109: =F136 -> 433.94377 | G109: =G136 -> 505.65636 | H109: =H136 -> 463.23365 | I109: =I136 -> 2477.4315 | J109: =J136 -> 147.38431 | K109: =K136 -> 1079.364 | L109: =L136 -> 1076.8362 | ... P109: =P136 -> 9294.4757
A110: Cash from Operations | D110: =D107+D108-D109 -> 11813.297 | E110: =E107+E108-E109 -> 13677.262 | F110: =F107+F108-F109 -> 17272.206 | G110: =G107+G108-G109 -> 18920.664 | H110: =H107+H108-H109 -> 19247.905 | I110: =I107+I108-I109 -> 20926.157 | J110: =J107+J108-J109 -> 28274.493 | K110: =K107+K108-K109 -> 32190.447 | ... P110: =P107+P108-P109 -> 2407.3183
A112: Investing Cash Flow
A113: Investments in Property & Equipment | D113: -8401 | E113: -8401 | F113: -8401 | G113: -8401 | H113: -8401 | I113: =-I140 -> -5750 | J113: =-J140 -> -5750 | K113: =-K140 -> -5750 | L113: =-L140 -> -5750 | M113: =-M140 -> -5750 | N113: =-N140 -> -5750 | O113: =-O140 -> -2875 | P113: =-P140 -> -2875
A114: Investments in Businesses
A115: Cash from Investing | D115: =SUM(D113:D114) -> -8401 | E115: =SUM(E113:E114) -> -8401 | F115: =SUM(F113:F114) -> -8401 | G115: =SUM(G113:G114) -> -8401 | H115: =SUM(H113:H114) -> -8401 | I115: =SUM(I113:I114) -> -5750 | J115: =SUM(J113:J114) -> -5750 | K115: =SUM(K113:K114) -> -5750 | ... P115: =SUM(P113:P114) -> -2875
A117: Financing Cash Flow
A118: Issuance (repayment) of debt | D118: 0 | E118: 0 | F118: ='[2]Target statements'!$E$46 -> -11199 | G118: 0 | H118: 0 | I118: =I146 -> 0 | J118: =J146 -> 0 | K118: =K146 -> 0 | L118: =L146 -> 0 | M118: =M146 -> 0 | N118: =N146 -> -10000 | O118: =O146 -> 0 | P118: =P146 -> 0
A119: Issuance (repayment) of equity | E119: 0 | F119: 0 | G119: 0 | H119: 0 | I119: =I57 -> 0 | J119: =J57 -> 0 | K119: =K57 -> 0 | L119: =L57 -> 0 | M119: =M57 -> 0 | N119: =N57 -> 0 | O119: =O57 -> 0 | P119: =P57 -> 0
A120: Payment of Dividends | D120: 0 | E120: 0 | F120: 0 | G120: 0 | H120: 0 | I120: =-I58 -> 0 | J120: =-J58 -> 0 | K120: =-K58 -> 0 | L120: =-L58 -> 0 | M120: =-M58 -> -200 | N120: =-N58 -> -200 | O120: =-O58 -> 0 | P120: =-P58 -> 0
A121: Cash from Financing | D121: =SUM(D118:D120) -> 0 | E121: =SUM(E118:E120) -> 0 | F121: =SUM(F118:F120) -> -11199 | G121: =SUM(G118:G120) -> 0 | H121: =SUM(H118:H120) -> 0 | I121: =SUM(I118:I120) -> 0 | J121: =SUM(J118:J120) -> 0 | K121: =SUM(K118:K120) -> 0 | ... P121: =SUM(P118:P120) -> 0
...
